Workbook

Sheet 00_Index
A1: AAH Financial Statement Format Library — Final Preparation Baseline
A3: No. | B3: Code | C3: Profile | D3: Authority | E3: Face Statements | F3: Notes / Schedules | G3: Special Statements | H3: AAH Mapping Ready
A4: 1 | B4: C_AS | C4: Company — AS — Schedule III Division I | D4: MCA | E4: Balance Sheet + P&L / equivalent | F4: Detailed linked note lines | G4: — | H4: Yes
A5: 2 | B5: C_IND | C5: Company — Ind AS — Schedule III Division II | D5: MCA | E5: Balance Sheet + P&L / equivalent | F5: Detailed linked note lines | G5: Statement of Changes in Equity, Cash Flow Statement | H5: Yes
A6: 3 | B6: NBFC_AS | C6: NBFC — Accounting Standards (non-Ind AS) | D6: MCA + RBI | E6: Balance Sheet + P&L / equivalent | F6: Detailed linked note lines | G6: RBI Regulatory Disclosure Pack | H6: Yes
A7: 4 | B7: NBFC_IND | C7: NBFC — Ind AS — Schedule III Division III | D7: MCA + RBI | E7: Balance Sheet + P&L / equivalent | F7: Detailed linked note lines | G7: Statement of Changes in Equity, Cash Flow Statement, RBI Regulatory Disclosure Pack | H7: Yes
A8: 5 | B8: NCE | C8: Non-Corporate Entity | D8: ICAI | E8: Balance Sheet + P&L / equivalent | F8: Detailed linked note lines | G8: Cash Flow Statement where applicable | H8: Yes
A9: 6 | B9: LLP | C9: Limited Liability Partnership | D9: ICAI + MCA | E9: Balance Sheet + P&L / equivalent | F9: Detailed linked note lines | G9: Cash Flow Statement where applicable, MCA Form 8 support output | H9: Yes
A10: 7 | B10: NPO | C10: Not-for-Profit Organisation | D10: ICAI / governing statute | E10: Balance Sheet + P&L / equivalent | F10: Detailed linked note lines | G10: Receipts & Payments where required, Fund movement schedules | H10: Yes
A11: 8 | B11: BANK | C11: Banking Company | D11: RBI / Banking Regulation Act | E11: Balance Sheet + P&L / equivalent | F11: Detailed linked note lines | G11: Form A Balance Sheet, Form B P&L, Schedules 1-16 | H11: Yes
A12: 9 | B12: COOPBANK | C12: Co-operative Bank | D12: RBI / Banking Regulation Act as adapted | E12: Balance Sheet + P&L / equivalent | F12: Detailed linked note lines | G12: Co-operative-bank adapted schedules, Overdue Interest Reserve disclosure | H12: Yes
A13: 10 | B13: LIFE | C13: Life Insurance | D13: IRDAI | E13: Balance Sheet + P&L / equivalent | F13: Detailed linked note lines | G13: Form A-BS, Form A-RA, Form A-PL | H13: Yes
A14: 11 | B14: GENINS | C14: General Insurance | D14: IRDAI | E14: Balance Sheet + P&L / equivalent | F14: Detailed linked note lines | G14: Form B-BS, Form B-RA, Form B-PL | H14: Yes
A15: 12 | B15: REINS | C15: Reinsurance | D15: IRDAI | E15: Balance Sheet + P&L / equivalent | F15: Detailed linked note lines | G15: Reinsurance-specific B-series forms, Regulatory reserve disclosures | H15: Yes
... A19: 16 | B19: INVIT | C19: Infrastructure Investment Trust | D19: SEBI | E19: Balance Sheet + P&L / equivalent | F19: Detailed linked note lines | G19: Statement of Changes in Unitholders' Equity, Cash Flow Statement, Statement of Net Assets at Fair Value, Statement of Total Returns at Fair Value, NDCF / Distribution Statement | H19: Yes

Sheet 01_Workflow
A1: Standard Financial Statement Preparation Workflow
A3: Step | B3: Stage | C3: What happens | D3: AAH authority | E3: User role | F3: Output
A4: 1 | B4: Profile | C4: Select legal/accounting/regulatory profile | D4: Client + FY | E4: Confirm | F4: Correct statutory schema
A5: 2 | B5: Data authority | C5: Bring current + comparative ledger balances | D5: AAH/Tally sync | E5: Review only | F5: Trial balance authority
A6: 3 | B6: Mapping | C6: Map ledger/group to AAH Mapping Key | D6: Persistent by MasterId | E6: Resolve unmapped | F6: Note allocation
A7: 4 | B7: Disclosures | C7: Capture non-ledger facts / statutory tables | D7: Client + FY | E7: Enter/approve | F7: Supplementary disclosure authority
A8: 5 | B8: Notes | C8: Aggregate mapping keys into note lines | D8: Calculated | E8: Review | F8: Complete Notes
A9: 6 | B9: Face statements | C9: Notes feed BS/P&L/I&E/Revenue Account | D9: Calculated | E9: None | F9: Final statements
A10: 7 | B10: Special statements | C10: CFS/SOCE/NAV/NDCF/regulatory schedules | D10: Calculated | E10: Review | F10: Complete report set
A11: 8 | B11: Validation | C11: Tie-outs, balance, mapping completeness, comparatives | D11: Calculated | E11: Resolve failures | F11: Ready status
A12: 9 | B12: Print pack | C12: Only clean final statements and notes | D12: Calculated | E12: Export / sign | F12: Excel/PDF-ready pack
A13: 10 | B13: Year rollover | C13: Carry mapping, not manual amounts | D13: AAH | E13: Review changes | F13: Next-year comparative setup

Sheet 02_Sources
A1: Official Source Register
A3: Profile | B3: Authority | C3: Official URL | D3: Rule
A4: Company — AS — Schedule III Division I | B4: MCA | C4: https://www.mca.gov.in/Ministry/pdf/ScheduleIIIAmendmentNotification_24032021.pdf | D4: Specific regulator/statute presentation overrides a generic format.
A5: Company — Ind AS — Schedule III Division II | B5: MCA | C5: https://www.mca.gov.in/Ministry/pdf/ScheduleIIIAmendmentNotification_24032021.pdf | D5: Specific regulator/statute presentation overrides a generic format.
A6: NBFC — Accounting Standards (non-Ind AS) | B6: MCA + RBI | C6: https://www.rbi.org.in/ | D6: Specific regulator/statute presentation overrides a generic format.
A7: NBFC — Ind AS — Schedule III Division III | B7: MCA + RBI | C7: https://www.mca.gov.in/Ministry/pdf/NotificationScheduleIII_12102018.pdf | D7: Specific regulator/statute presentation overrides a generic format.
A8: Non-Corporate Entity | B8: ICAI | C8: https://www.icai.org/post/guidance-notes | D8: Specific regulator/statute presentation overrides a generic format.
A9: Limited Liability Partnership | B9: ICAI + MCA | C9: https://www.icai.org/post/guidance-notes | D9: Specific regulator/statute presentation overrides a generic format.
A10: Not-for-Profit Organisation | B10: ICAI / governing statute | C10: https://www.icai.org/post/technical-guides-and-other-materials | D10: Specific regulator/statute presentation overrides a generic format.
A11: Banking Company | B11: RBI / Banking Regulation Act | C11: https://www.indiacode.nic.in/bitstream/123456789/1885/1/A194910.pdf | D11: Specific regulator/statute presentation overrides a generic format.
A12: Co-operative Bank | B12: RBI / Banking Regulation Act as adapted | C12: https://www.rbi.org.in/ | D12: Specific regulator/statute presentation overrides a generic format.
A13: Life Insurance | B13: IRDAI | C13: https://irdai.gov.in/ | D13: Specific regulator/statute presentation overrides a generic format.
A14: General Insurance | B14: IRDAI | C14: https://irdai.gov.in/ | D14: Specific regulator/statute presentation overrides a generic format.
... A19: Infrastructure Investment Trust | B19: SEBI | C19: https://www.sebi.gov.in/sebi_data/attachdocs/jul-2025/1752576381910.pdf | D19: Specific regulator/statute presentation overrides a generic format.

Sheet C_AS
A1: Company — AS — Schedule III Division I
A2: Authority: MCA | Official source: https://www.mca.gov.in/Ministry/pdf/ScheduleIIIAmendmentNotification_24032021.pdf
A3: =IF('AAH Basic Info'!B5="","","Address: "&'AAH Basic Info'!B5) | B3: =IF('AAH Basic Info'!B6="","","PAN: "&'AAH Basic Info'!B6) | C3: =IF('AAH Basic Info'!B7="","","GSTIN: "&'AAH Basic Info'!B7) | D3: =IF('AAH Basic Info'!B27="","",'AAH Basic Info'!B27)
A4: Entity Name | B4: Current Period | C4: Previous Period | D4: Presentation Unit | E4: Standalone / Consolidated
A5: =IF('AAH Basic Info'!B3="","",'AAH Basic Info'!B3) | B5: =IF('AAH Basic Info'!B9="","",'AAH Basic Info'!B9) | C5: =IF('AAH Basic Info'!B10="","",'AAH Basic Info'!B10) | D5: =IF('AAH Basic Info'!B24="","",'AAH Basic Info'!B24) | E5: =IF('AAH Basic Info'!B25="","",'AAH Basic Info'!B25)
A6: Balance Sheet / Statement of Financial Position
A7: Particulars | B7: Note No. | C7: Current Reporting Period | D7: Previous Reporting Period
A8: EQUITY AND LIABILITIES
A9: 1. Shareholders' Funds
A10: Share Capital | B10: 1 | C10: =E75 | D10: =F75
A11: Reserves and Surplus | B11: 2 | C11: =E83 | D11: =F83
A12: 2. Share Application Money Pending Allotment
A13: Share Application Money Pending Allotment | B13: —
A14: 3. Non-current Liabilities
A15: Long-term Borrowings | B15: 3 | C15: =E92 | D15: =F92
A16: Deferred Tax Liabilities (Net) | B16: 4 | C16: =E94 | D16: =F94
A17: Other Long-term Liabilities | B17: 5 | C17: =E98 | D17: =F98
A18: Long-term Provisions | B18: 6 | C18: =E101 | D18: =F101
A19: 4. Current Liabilities
A20: Short-term Borrowings | B20: 7 | C20: =E107 | D20: =F107
A21: Trade Payables | B21: 8 | C21: =E112 | D21: =F112
A22: Other Current Liabilities | B22: 9 | C22: =E121 | D22: =F121
A23: Short-term Provisions | B23: 10 | C23: =E125 | D23: =F125
A24: TOTAL EQUITY AND LIABILITIES | C24: =SUM(C10,C11,C13,C15,C16,C17,C18,C20,C21,C22,C23) | D24: =SUM(D10,D11,D13,D15,D16,D17,D18,D20,D21,D22,D23)
A25: ASSETS
A26: 1. Non-current Assets
A27: Property, Plant and Equipment / Intangibles / CWIP | B27: 11 | C27: =E135 | D27: =F135
A28: Non-current Investments | B28: 12 | C28: =E144 | D28: =F144
A29: Deferred Tax Assets (Net) | B29: 4 | C29: =E93 | D29: =F93
A30: Long-term Loans and Advances | B30: 13 | C30: =E150 | D30: =F150
A31: Other Non-current Assets | B31: 14 | C31: =E154 | D31: =F154
A32: 2. Current Assets
A33: Current Investments | B33: 15 | C33: =E158 | D33: =F158
A34: Inventories | B34: 16 | C34: =E167 | D34: =F167
A35: Trade Receivables | B35: 17 | C35: =E173 | D35: =F173
A36: Cash and Cash Equivalents | B36: 18 | C36: =E178 | D36: =F178
A37: Short-term Loans and Advances | B37: 19 | C37: =E182 | D37: =F182
A38: Other Current Assets | B38: 20 | C38: =E187 | D38: =F187
A39: TOTAL ASSETS | C39: =SUM(C27,C28,C29,C30,C31,C33,C34,C35,C36,C37,C38) | D39: =SUM(D27,D28,D29,D30,D31,D33,D34,D35,D36,D37,D38)
A42: Statement of Profit & Loss / Income & Expenditure / Revenue Account
A43: Particulars | B43: Note No. | C43: Current Reporting Period | D43: Previous Reporting Period
A44: Revenue from Operations | B44: 21 | C44: =E192 | D44: =F192
A45: Other Income | B45: 22 | C45: =E197 | D45: =F197
A46: TOTAL INCOME | C46: =SUM(C44,C45) | D46: =SUM(D44,D45)
A47: EXPENSES
A48: Cost of Materials Consumed | B48: 23 | C48: =E202 | D48: =F202
A49: Purchases of Stock-in-Trade | B49: 24 | C49: =E204 | D49: =F204
A50: Changes in Inventories | B50: 25 | C50: =E207 | D50: =F207
A51: Employee Benefits Expense | B51: 26 | C51: =E212 | D51: =F212
A52: Finance Costs | B52: 27 | C52: =E216 | D52: =F216
A53: Depreciation and Amortisation Expense | B53: 28 | C53: =E219 | D53: =F219
A54: Other Expenses | B54: 29 | C54: =E230 | D54: =F230
A55: TOTAL EXPENSES | C55: =SUM(C48,C49,C50,C51,C52,C53,C54) | D55: =SUM(D48,D49,D50,D51,D52,D53,D54)
A56: Profit/(Loss) before Exceptional and Extraordinary Items and Tax | C56: =C46-C55 | D56: =D46-D55
A57: Exceptional Items | B57: —
A58: Profit/(Loss) before Extraordinary Items and Tax | C58: =C56-SUM(C57) | D58: =D56-SUM(D57)
A59: Extraordinary Items | B59: —
A60: Profit Before Tax | C60: =C58-SUM(C59) | D60: =D58-SUM(D59)
A61: Current Tax | B61: —
A62: Earlier-year Tax Adjustment | B62: —
A63: Deferred Tax Charge / (Benefit) | B63: —
A64: Profit/(Loss) for the Period | C64: =C60-SUM(C61,C62,C63) | D64: =D60-SUM(D61,D62,D63)
A67: Notes / Schedules — linked source for face statements
A68: Note | B68: Note Title | C68: Statutory Line Item | D68: AAH Mapping Key | E68: Current Period | F68: Previous Period | G68: Disclosure / Remarks
A69: 1 | B69: Share Capital | C69: Authorised share capital | D69: SC_AUTH | E69: 0 | F69: 0
A70: 1 | B70: Share Capital | C70: Issued share capital | D70: SC_ISSUED | E70: 0 | F70: 0
A71: 1 | B71: Share Capital | C71: Subscribed and fully paid-up capital | D71: SC_PAID | E71: 0 | F71: 0
A72: 1 | B72: Share Capital | C72: Subscribed but not fully paid-up capital | D72: SC_PARTPAID | E72: 0 | F72: 0
A73: 1 | B73: Share Capital | C73: Calls unpaid | D73: SC_CALLS_UNPAID | E73: 0 | F73: 0
A74: 1 | B74: Share Capital | C74: Forfeited shares | D74: SC_FORFEIT | E74: 0 | F74: 0
A75: 1 | B75: Share Capital | C75: Total — Share Capital | D75: __TOTAL__ | E75: =SUM(E69:E74) | F75: =SUM(F69:F74)
A76: 2 | B76: Reserves and Surplus | C76: Capital reserve | D76: RES_CAPITAL | E76: 0 | F76: 0
A77: 2 | B77: Reserves and Surplus | C77: Capital redemption reserve | D77: RES_CRR | E77: 0 | F77: 0
A78: 2 | B78: Reserves and Surplus | C78: Securities premium | D78: RES_SP | E78: 0 | F78: 0
A79: 2 | B79: Reserves and Surplus | C79: Debenture redemption reserve | D79: RES_DRR | E79: 0 | F79: 0
A80: 2 | B80: Reserves and Surplus | C80: Revaluation reserve | D80: RES_REVAL | E80: 0 | F80: 0
A81: 2 | B81: Reserves and Surplus | C81: Other reserves | D81: RES_OTHER | E81: 0 | F81: 0
A82: 2 | B82: Reserves and Surplus | C82: Surplus / (deficit) in Statement of P&L | D82: RES_SURPLUS | E82: 0 | F82: 0
A83: 2 | B83: Reserves and Surplus | C83: Total — Reserves and Surplus | D83: __TOTAL__ | E83: =SUM(E76:E82) | F83: =SUM(F76:F82)
A84: 3 | B84: Long-term Borrowings | C84: Bonds / debentures | D84: LTB_BONDS | E84: 0 | F84: 0
A85: 3 | B85: Long-term Borrowings | C85: Term loans from banks | D85: LTB_BANK | E85: 0 | F85: 0
A86: 3 | B86: Long-term Borrowings | C86: Term loans from other parties | D86: LTB_OTHER | E86: 0 | F86: 0
A87: 3 | B87: Long-term Borrowings | C87: Deferred payment liabilities | D87: LTB_DEFERRED | E87: 0 | F87: 0
A88: 3 | B88: Long-term Borrowings | C88: Deposits | D88: LTB_DEPOSITS | E88: 0 | F88: 0
A89: 3 | B89: Long-term Borrowings | C89: Loans from related parties | D89: LTB_RELATED | E89: 0 | F89: 0
A90: 3 | B90: Long-term Borrowings | C90: Finance lease obligations | D90: LTB_LEASE | E90: 0 | F90: 0
A91: 3 | B91: Long-term Borrowings | C91: Other loans / advances | D91: LTB_OTHERLOAN | E91: 0 | F91: 0
A92: 3 | B92: Long-term Borrowings | C92: Total — Long-term Borrowings | D92: __TOTAL__ | E92: =SUM(E84:E91) | F92: =SUM(F84:F91)
A93: 4 | B93: Deferred Tax | C93: Deferred tax asset | D93: DTA | E93: 0 | F93: 0
A94: 4 | B94: Deferred Tax | C94: Deferred tax liability | D94: DTL | E94: 0 | F94: 0
A95: 4 | B95: Deferred Tax | C95: Total — Deferred Tax | D95: __TOTAL__ | E95: =SUM(E93:E94) | F95: =SUM(F93:F94)
A96: 5 | B96: Other Long-term Liabilities | C96: Trade payables - non-current | D96: OLTL_TP | E96: 0 | F96: 0
A97: 5 | B97: Other Long-term Liabilities | C97: Security deposits / other long-term liabilities | D97: OLTL_OTHER | E97: 0 | F97: 0
A98: 5 | B98: Other Long-term Liabilities | C98: Total — Other Long-term Liabilities | D98: __TOTAL__ | E98: =SUM(E96:E97) | F98: =SUM(F96:F97)
A99: 6 | B99: Long-term Provisions | C99: Employee benefit provisions | D99: LTP_EMP | E99: 0 | F99: 0
A100: 6 | B100: Long-term Provisions | C100: Other long-term provisions | D100: LTP_OTHER | E100: 0 | F100: 0
A101: 6 | B101: Long-term Provisions | C101: Total — Long-term Provisions | D101: __TOTAL__ | E101: =SUM(E99:E100) | F101: =SUM(F99:F100)
A102: 7 | B102: Short-term Borrowings | C102: Loans repayable on demand - banks | D102: STB_BANK_OD | E102: 0 | F102: 0
A103: 7 | B103: Short-term Borrowings | C103: Loans repayable on demand - others | D103: STB_OTHER_OD | E103: 0 | F103: 0
A104: 7 | B104: Short-term Borrowings | C104: Loans from related parties | D104: STB_RELATED | E104: 0 | F104: 0
...

Sheet C_IND
A1: Company — Ind AS — Schedule III Division II
A2: Authority: MCA | Official source: https://www.mca.gov.in/Ministry/pdf/ScheduleIIIAmendmentNotification_24032021.pdf
A3: =IF('AAH Basic Info'!B5="","","Address: "&'AAH Basic Info'!B5) | B3: =IF('AAH Basic Info'!B6="","","PAN: "&'AAH Basic Info'!B6) | C3: =IF('AAH Basic Info'!B7="","","GSTIN: "&'AAH Basic Info'!B7) | D3: =IF('AAH Basic Info'!B27="","",'AAH Basic Info'!B27)
A4: Entity Name | B4: Current Period | C4: Previous Period | D4: Presentation Unit | E4: Standalone / Consolidated
A5: =IF('AAH Basic Info'!B3="","",'AAH Basic Info'!B3) | B5: =IF('AAH Basic Info'!B9="","",'AAH Basic Info'!B9) | C5: =IF('AAH Basic Info'!B10="","",'AAH Basic Info'!B10) | D5: =IF('AAH Basic Info'!B24="","",'AAH Basic Info'!B24) | E5: =IF('AAH Basic Info'!B25="","",'AAH Basic Info'!B25)
A6: Balance Sheet / Statement of Financial Position
A7: Particulars | B7: Note No. | C7: Current Reporting Period | D7: Previous Reporting Period
A8: ASSETS
A9: 1. Non-current Assets
A10: Property, Plant and Equipment | B10: 1 | C10: =E83 | D10: =F83
A11: Capital Work-in-Progress | B11: 2 | C11: =E85 | D11: =F85
A12: Investment Property | B12: 3 | C12: =E87 | D12: =F87
A13: Goodwill | B13: 4 | C13: =E89 | D13: =F89
A14: Other Intangible Assets | B14: 5 | C14: =E91 | D14: =F91
A15: Intangible Assets under Development | B15: 6 | C15: =E93 | D15: =F93
A16: Biological Assets other than Bearer Plants | B16: 7 | C16: =E95 | D16: =F95
A17: Financial Assets - Investments | B17: 8 | C17: =E99 | D17: =F99
A18: Financial Assets - Trade Receivables | B18: 9 | C18: =E102 | D18: =F102
A19: Financial Assets - Loans | B19: 10 | C19: =E104 | D19: =F104
A20: Other Financial Assets | B20: 11 | C20: =E106 | D20: =F106
A21: Deferred Tax Assets (Net) | B21: 12 | C21: =E107 | D21: =F107
A22: Other Non-current Assets | B22: 13 | C22: =E111 | D22: =F111
A23: 2. Current Assets
A24: Inventories | B24: 14 | C24: =E117 | D24: =F117
A25: Financial Assets - Investments | B25: 8 | C25: =E99 | D25: =F99
A26: Financial Assets - Trade Receivables | B26: 9 | C26: =E102 | D26: =F102
A27: Cash and Cash Equivalents | B27: 16 | C27: =E124 | D27: =F124
A28: Bank Balances other than Cash Equivalents | B28: 17 | C28: =E126 | D28: =F126
A29: Financial Assets - Loans | B29: 10 | C29: =E104 | D29: =F104
A30: Other Financial Assets | B30: 11 | C30: =E106 | D30: =F106
A31: Current Tax Assets (Net) | B31: 15 | C31: =E118 | D31: =F118
A32: Other Current Assets | B32: 18 | C32: =E128 | D32: =F128
A33: TOTAL ASSETS | C33: =SUM(C10,C11,C12,C13,C14,C15,C16,C17,C18,C19,C20,C21,C22,C24,C25,C26,C27,C28,C29,C30,C31,C32) | D33: =SUM(D10,D11,D12,D13,D14,D15,D16,D17,D18,D19,D20,D21,D22,D24,D25,D26,D27,D28,D29,D30,D31,D32)
A34: EQUITY AND LIABILITIES
A35: Equity
A36: Equity Share Capital | B36: 19 | C36: =E130 | D36: =F130
A37: Other Equity | B37: 20 | C37: =E135 | D37: =F135
A38: Non-current Liabilities
A39: Financial Liabilities - Borrowings | B39: 21 | C39: =E137 | D39: =F137
A40: Trade Payables | B40: 22 | C40: =E140 | D40: =F140
A41: Other Financial Liabilities | B41: 23 | C41: =E142 | D41: =F142
A42: Provisions | B42: 24 | C42: =E145 | D42: =F145
A43: Deferred Tax Liabilities (Net) | B43: 12 | C43: =E108 | D43: =F108
A44: Other Non-current Liabilities | B44: 25 | C44: =E149 | D44: =F149
A45: Current Liabilities
A46: Financial Liabilities - Borrowings | B46: 21 | C46: =E137 | D46: =F137
A47: Trade Payables | B47: 22 | C47: =E140 | D47: =F140
A48: Other Financial Liabilities | B48: 23 | C48: =E142 | D48: =F142
A49: Other Current Liabilities | B49: 25 | C49: =E149 | D49: =F149
A50: Provisions | B50: 24 | C50: =E145 | D50: =F145
A51: Current Tax Liabilities (Net) | B51: 15 | C51: =E119 | D51: =F119
A52: TOTAL EQUITY AND LIABILITIES | C52: =SUM(C36,C37,C39,C40,C41,C42,C43,C44,C46,C47,C48,C49,C50,C51) | D52: =SUM(D36,D37,D39,D40,D41,D42,D43,D44,D46,D47,D48,D49,D50,D51)
A55: Statement of Profit & Loss / Income & Expenditure / Revenue Account
A56: Particulars | B56: Note No. | C56: Current Reporting Period | D56: Previous Reporting Period
A57: Revenue from Operations | B57: 26 | C57: =E153 | D57: =F153
A58: Other Income | B58: 27 | C58: =E157 | D58: =F157
A59: TOTAL INCOME | C59: =SUM(C57,C58) | D59: =SUM(D57,D58)
A60: EXPENSES
A61: Cost of Materials Consumed | B61: 28 | C61: =E159 | D61: =F159
A62: Purchases of Stock-in-Trade | B62: 29 | C62: =E161 | D62: =F161
A63: Changes in Inventories | B63: 30 | C63: =E163 | D63: =F163
A64: Employee Benefits Expense | B64: 31 | C64: =E165 | D64: =F165
A65: Finance Costs | B65: 32 | C65: =E167 | D65: =F167
A66: Depreciation and Amortisation | B66: 33 | C66: =E170 | D66: =F170
A67: Other Expenses | B67: 34 | C67: =E172 | D67: =F172
A68: TOTAL EXPENSES | C68: =SUM(C61,C62,C63,C64,C65,C66,C67) | D68: =SUM(D61,D62,D63,D64,D65,D66,D67)
A69: Profit Before Tax | C69: =C59-C68 | D69: =D59-D68
A70: Current Tax | B70: —
A71: Deferred Tax | B71: —
A72: Profit for the Period | C72: =C69-SUM(C70,C71) | D72: =D69-SUM(D70,D71)
A73: Other Comprehensive Income | B73: 35 | C73: =E176 | D73: =F176
A74: Total Comprehensive Income | C74: =C72+SUM(C73) | D74: =D72+SUM(D73)
A77: Notes / Schedules — linked source for face statements
A78: Note | B78: Note Title | C78: Statutory Line Item | D78: AAH Mapping Key | E78: Current Period | F78: Previous Period | G78: Disclosure / Remarks
A79: 1 | B79: Property, Plant and Equipment | C79: Land | D79: PPE_LAND | E79: 0 | F79: 0
A80: 1 | B80: Property, Plant and Equipment | C80: Buildings | D80: PPE_BUILD | E80: 0 | F80: 0
A81: 1 | B81: Property, Plant and Equipment | C81: Plant and equipment | D81: PPE_PLANT | E81: 0 | F81: 0
A82: 1 | B82: Property, Plant and Equipment | C82: Other PPE | D82: PPE_OTHER | E82: 0 | F82: 0
A83: 1 | B83: Property, Plant and Equipment | C83: Total — Property, Plant and Equipment | D83: __TOTAL__ | E83: =SUM(E79:E82) | F83: =SUM(F79:F82)
A84: 2 | B84: Capital Work-in-Progress | C84: CWIP | D84: CWIP | E84: 0 | F84: 0
A85: 2 | B85: Capital Work-in-Progress | C85: Total — Capital Work-in-Progress | D85: __TOTAL__ | E85: =SUM(E84:E84) | F85: =SUM(F84:F84)
A86: 3 | B86: Investment Property | C86: Investment property | D86: INVPROP | E86: 0 | F86: 0
A87: 3 | B87: Investment Property | C87: Total — Investment Property | D87: __TOTAL__ | E87: =SUM(E86:E86) | F87: =SUM(F86:F86)
A88: 4 | B88: Goodwill | C88: Goodwill | D88: GOODWILL | E88: 0 | F88: 0
A89: 4 | B89: Goodwill | C89: Total — Goodwill | D89: __TOTAL__ | E89: =SUM(E88:E88) | F89: =SUM(F88:F88)
A90: 5 | B90: Other Intangible Assets | C90: Intangible assets | D90: INTANG | E90: 0 | F90: 0
A91: 5 | B91: Other Intangible Assets | C91: Total — Other Intangible Assets | D91: __TOTAL__ | E91: =SUM(E90:E90) | F91: =SUM(F90:F90)
A92: 6 | B92: Intangible Assets under Development | C92: IAUD | D92: IAUD | E92: 0 | F92: 0
A93: 6 | B93: Intangible Assets under Development | C93: Total — Intangible Assets under Development | D93: __TOTAL__ | E93: =SUM(E92:E92) | F93: =SUM(F92:F92)
A94: 7 | B94: Biological Assets other than Bearer Plants | C94: Biological assets | D94: BIOASSET | E94: 0 | F94: 0
A95: 7 | B95: Biological Assets other than Bearer Plants | C95: Total — Biological Assets other than Bearer Plants | D95: __TOTAL__ | E95: =SUM(E94:E94) | F95: =SUM(F94:F94)
A96: 8 | B96: Financial Assets - Investments | C96: Equity instruments | D96: FININV_EQUITY | E96: 0 | F96: 0
A97: 8 | B97: Financial Assets - Investments | C97: Debt instruments | D97: FININV_DEBT | E97: 0 | F97: 0
A98: 8 | B98: Financial Assets - Investments | C98: Other investments | D98: FININV_OTHER | E98: 0 | F98: 0
A99: 8 | B99: Financial Assets - Investments | C99: Total — Financial Assets - Investments | D99: __TOTAL__ | E99: =SUM(E96:E98) | F99: =SUM(F96:F98)
A100: 9 | B100: Financial Assets - Trade Receivables | C100: Trade receivables | D100: FA_TR | E100: 0 | F100: 0
A101: 9 | B101: Financial Assets - Trade Receivables | C101: Allowance | D101: FA_TR_ALLOW | E101: 0 | F101: 0
A102: 9 | B102: Financial Assets - Trade Receivables | C102: Total — Financial Assets - Trade Receivables | D102: __TOTAL__ | E102: =SUM(E100:E101) | F102: =SUM(F100:F101)
A103: 10 | B103: Financial Assets - Loans | C103: Loans | D103: FA_LOANS | E103: 0 | F103: 0
A104: 10 | B104: Financial Assets - Loans | C104: Total — Financial Assets - Loans | D104: __TOTAL__ | E104: =SUM(E103:E103) | F104: =SUM(F103:F103)
...

Sheet NBFC_AS
A1: NBFC — Accounting Standards (non-Ind AS)
A2: Authority: MCA + RBI | Official source: https://www.rbi.org.in/
A3: =IF('AAH Basic Info'!B5="","","Address: "&'AAH Basic Info'!B5) | B3: =IF('AAH Basic Info'!B6="","","PAN: "&'AAH Basic Info'!B6) | C3: =IF('AAH Basic Info'!B7="","","GSTIN: "&'AAH Basic Info'!B7) | D3: =IF('AAH Basic Info'!B27="","",'AAH Basic Info'!B27)
A4: Entity Name | B4: Current Period | C4: Previous Period | D4: Presentation Unit | E4: Standalone / Consolidated
A5: =IF('AAH Basic Info'!B3="","",'AAH Basic Info'!B3) | B5: =IF('AAH Basic Info'!B9="","",'AAH Basic Info'!B9) | C5: =IF('AAH Basic Info'!B10="","",'AAH Basic Info'!B10) | D5: =IF('AAH Basic Info'!B24="","",'AAH Basic Info'!B24) | E5: =IF('AAH Basic Info'!B25="","",'AAH Basic Info'!B25)
A6: Balance Sheet / Statement of Financial Position
A7: Particulars | B7: Note No. | C7: Current Reporting Period | D7: Previous Reporting Period
A8: EQUITY AND LIABILITIES
A9: 1. Shareholders' Funds
A10: Share Capital | B10: 1 | C10: =E75 | D10: =F75
A11: Reserves and Surplus | B11: 2 | C11: =E83 | D11: =F83
A12: 2. Share Application Money Pending Allotment
A13: Share Application Money Pending Allotment | B13: —
A14: 3. Non-current Liabilities
A15: Long-term Borrowings | B15: 3 | C15: =E92 | D15: =F92
A16: Deferred Tax Liabilities (Net) | B16: 4 | C16: =E94 | D16: =F94
A17: Other Long-term Liabilities | B17: 5 | C17: =E98 | D17: =F98
A18: Long-term Provisions | B18: 6 | C18: =E101 | D18: =F101
A19: 4. Current Liabilities
A20: Short-term Borrowings | B20: 7 | C20: =E107 | D20: =F107
A21: Trade Payables | B21: 8 | C21: =E112 | D21: =F112
A22: Other Current Liabilities | B22: 9 | C22: =E121 | D22: =F121
A23: Short-term Provisions | B23: 10 | C23: =E125 | D23: =F125
A24: TOTAL EQUITY AND LIABILITIES | C24: =SUM(C10,C11,C13,C15,C16,C17,C18,C20,C21,C22,C23) | D24: =SUM(D10,D11,D13,D15,D16,D17,D18,D20,D21,D22,D23)
A25: ASSETS
A26: 1. Non-current Assets
A27: Property, Plant and Equipment / Intangibles / CWIP | B27: 11 | C27: =E135 | D27: =F135
A28: Non-current Investments | B28: 12 | C28: =E144 | D28: =F144
A29: Deferred Tax Assets (Net) | B29: 4 | C29: =E93 | D29: =F93
A30: Long-term Loans and Advances | B30: 13 | C30: =E150 | D30: =F150
A31: Other Non-current Assets | B31: 14 | C31: =E154 | D31: =F154
A32: 2. Current Assets
A33: Current Investments | B33: 15 | C33: =E158 | D33: =F158
A34: Inventories | B34: 16 | C34: =E167 | D34: =F167
A35: Trade Receivables | B35: 17 | C35: =E173 | D35: =F173
A36: Cash and Cash Equivalents | B36: 18 | C36: =E178 | D36: =F178
A37: Short-term Loans and Advances | B37: 19 | C37: =E182 | D37: =F182
A38: Other Current Assets | B38: 20 | C38: =E187 | D38: =F187
A39: TOTAL ASSETS | C39: =SUM(C27,C28,C29,C30,C31,C33,C34,C35,C36,C37,C38) | D39: =SUM(D27,D28,D29,D30,D31,D33,D34,D35,D36,D37,D38)
A42: Statement of Profit & Loss / Income & Expenditure / Revenue Account
A43: Particulars | B43: Note No. | C43: Current Reporting Period | D43: Previous Reporting Period
A44: Revenue from Operations | B44: 21 | C44: =E192 | D44: =F192
A45: Other Income | B45: 22 | C45: =E197 | D45: =F197
A46: TOTAL INCOME | C46: =SUM(C44,C45) | D46: =SUM(D44,D45)
A47: EXPENSES
A48: Cost of Materials Consumed | B48: 23 | C48: =E202 | D48: =F202
A49: Purchases of Stock-in-Trade | B49: 24 | C49: =E204 | D49: =F204
A50: Changes in Inventories | B50: 25 | C50: =E207 | D50: =F207
A51: Employee Benefits Expense | B51: 26 | C51: =E212 | D51: =F212
A52: Finance Costs | B52: 27 | C52: =E216 | D52: =F216
A53: Depreciation and Amortisation Expense | B53: 28 | C53: =E219 | D53: =F219
A54: Other Expenses | B54: 29 | C54: =E230 | D54: =F230
A55: TOTAL EXPENSES | C55: =SUM(C48,C49,C50,C51,C52,C53,C54) | D55: =SUM(D48,D49,D50,D51,D52,D53,D54)
A56: Profit/(Loss) before Exceptional and Extraordinary Items and Tax | C56: =C46-C55 | D56: =D46-D55
A57: Exceptional Items | B57: —
A58: Profit/(Loss) before Extraordinary Items and Tax | C58: =C56-SUM(C57) | D58: =D56-SUM(D57)
A59: Extraordinary Items | B59: —
A60: Profit Before Tax | C60: =C58-SUM(C59) | D60: =D58-SUM(D59)
A61: Current Tax | B61: —
A62: Earlier-year Tax Adjustment | B62: —
A63: Deferred Tax Charge / (Benefit) | B63: —
A64: Profit/(Loss) for the Period | C64: =C60-SUM(C61,C62,C63) | D64: =D60-SUM(D61,D62,D63)
A67: Notes / Schedules — linked source for face statements
A68: Note | B68: Note Title | C68: Statutory Line Item | D68: AAH Mapping Key | E68: Current Period | F68: Previous Period | G68: Disclosure / Remarks
A69: 1 | B69: Share Capital | C69: Authorised share capital | D69: SC_AUTH | E69: 0 | F69: 0
A70: 1 | B70: Share Capital | C70: Issued share capital | D70: SC_ISSUED | E70: 0 | F70: 0
A71: 1 | B71: Share Capital | C71: Subscribed and fully paid-up capital | D71: SC_PAID | E71: 0 | F71: 0
A72: 1 | B72: Share Capital | C72: Subscribed but not fully paid-up capital | D72: SC_PARTPAID | E72: 0 | F72: 0
A73: 1 | B73: Share Capital | C73: Calls unpaid | D73: SC_CALLS_UNPAID | E73: 0 | F73: 0
A74: 1 | B74: Share Capital | C74: Forfeited shares | D74: SC_FORFEIT | E74: 0 | F74: 0
A75: 1 | B75: Share Capital | C75: Total — Share Capital | D75: __TOTAL__ | E75: =SUM(E69:E74) | F75: =SUM(F69:F74)
A76: 2 | B76: Reserves and Surplus | C76: Capital reserve | D76: RES_CAPITAL | E76: 0 | F76: 0
A77: 2 | B77: Reserves and Surplus | C77: Capital redemption reserve | D77: RES_CRR | E77: 0 | F77: 0
A78: 2 | B78: Reserves and Surplus | C78: Securities premium | D78: RES_SP | E78: 0 | F78: 0
A79: 2 | B79: Reserves and Surplus | C79: Debenture redemption reserve | D79: RES_DRR | E79: 0 | F79: 0
A80: 2 | B80: Reserves and Surplus | C80: Revaluation reserve | D80: RES_REVAL | E80: 0 | F80: 0
A81: 2 | B81: Reserves and Surplus | C81: Other reserves | D81: RES_OTHER | E81: 0 | F81: 0
A82: 2 | B82: Reserves and Surplus | C82: Surplus / (deficit) in Statement of P&L | D82: RES_SURPLUS | E82: 0 | F82: 0
A83: 2 | B83: Reserves and Surplus | C83: Total — Reserves and Surplus | D83: __TOTAL__ | E83: =SUM(E76:E82) | F83: =SUM(F76:F82)
A84: 3 | B84: Long-term Borrowings | C84: Bonds / debentures | D84: LTB_BONDS | E84: 0 | F84: 0
A85: 3 | B85: Long-term Borrowings | C85: Term loans from banks | D85: LTB_BANK | E85: 0 | F85: 0
A86: 3 | B86: Long-term Borrowings | C86: Term loans from other parties | D86: LTB_OTHER | E86: 0 | F86: 0
A87: 3 | B87: Long-term Borrowings | C87: Deferred payment liabilities | D87: LTB_DEFERRED | E87: 0 | F87: 0
A88: 3 | B88: Long-term Borrowings | C88: Deposits | D88: LTB_DEPOSITS | E88: 0 | F88: 0
A89: 3 | B89: Long-term Borrowings | C89: Loans from related parties | D89: LTB_RELATED | E89: 0 | F89: 0
A90: 3 | B90: Long-term Borrowings | C90: Finance lease obligations | D90: LTB_LEASE | E90: 0 | F90: 0
A91: 3 | B91: Long-term Borrowings | C91: Other loans / advances | D91: LTB_OTHERLOAN | E91: 0 | F91: 0
A92: 3 | B92: Long-term Borrowings | C92: Total — Long-term Borrowings | D92: __TOTAL__ | E92: =SUM(E84:E91) | F92: =SUM(F84:F91)
A93: 4 | B93: Deferred Tax | C93: Deferred tax asset | D93: DTA | E93: 0 | F93: 0
A94: 4 | B94: Deferred Tax | C94: Deferred tax liability | D94: DTL | E94: 0 | F94: 0
A95: 4 | B95: Deferred Tax | C95: Total — Deferred Tax | D95: __TOTAL__ | E95: =SUM(E93:E94) | F95: =SUM(F93:F94)
A96: 5 | B96: Other Long-term Liabilities | C96: Trade payables - non-current | D96: OLTL_TP | E96: 0 | F96: 0
A97: 5 | B97: Other Long-term Liabilities | C97: Security deposits / other long-term liabilities | D97: OLTL_OTHER | E97: 0 | F97: 0
A98: 5 | B98: Other Long-term Liabilities | C98: Total — Other Long-term Liabilities | D98: __TOTAL__ | E98: =SUM(E96:E97) | F98: =SUM(F96:F97)
A99: 6 | B99: Long-term Provisions | C99: Employee benefit provisions | D99: LTP_EMP | E99: 0 | F99: 0
A100: 6 | B100: Long-term Provisions | C100: Other long-term provisions | D100: LTP_OTHER | E100: 0 | F100: 0
A101: 6 | B101: Long-term Provisions | C101: Total — Long-term Provisions | D101: __TOTAL__ | E101: =SUM(E99:E100) | F101: =SUM(F99:F100)
A102: 7 | B102: Short-term Borrowings | C102: Loans repayable on demand - banks | D102: STB_BANK_OD | E102: 0 | F102: 0
A103: 7 | B103: Short-term Borrowings | C103: Loans repayable on demand - others | D103: STB_OTHER_OD | E103: 0 | F103: 0
A104: 7 | B104: Short-term Borrowings | C104: Loans from related parties | D104: STB_RELATED | E104: 0 | F104: 0
...

Sheet NBFC_IND
A1: NBFC — Ind AS — Schedule III Division III
A2: Authority: MCA + RBI | Official source: https://www.mca.gov.in/Ministry/pdf/NotificationScheduleIII_12102018.pdf
A3: =IF('AAH Basic Info'!B5="","","Address: "&'AAH Basic Info'!B5) | B3: =IF('AAH Basic Info'!B6="","","PAN: "&'AAH Basic Info'!B6) | C3: =IF('AAH Basic Info'!B7="","","GSTIN: "&'AAH Basic Info'!B7) | D3: =IF('AAH Basic Info'!B27="","",'AAH Basic Info'!B27)
A4: Entity Name | B4: Current Period | C4: Previous Period | D4: Presentation Unit | E4: Standalone / Consolidated
A5: =IF('AAH Basic Info'!B3="","",'AAH Basic Info'!B3) | B5: =IF('AAH Basic Info'!B9="","",'AAH Basic Info'!B9) | C5: =IF('AAH Basic Info'!B10="","",'AAH Basic Info'!B10) | D5: =IF('AAH Basic Info'!B24="","",'AAH Basic Info'!B24) | E5: =IF('AAH Basic Info'!B25="","",'AAH Basic Info'!B25)
A6: Balance Sheet / Statement of Financial Position
A7: Particulars | B7: Note No. | C7: Current Reporting Period | D7: Previous Reporting Period
A8: ASSETS
A9: Financial Assets
A10: Cash and Cash Equivalents | B10: 1 | C10: =E82 | D10: =F82
A11: Bank Balance other than above | B11: 2 | C11: =E84 | D11: =F84
A12: Derivative Financial Instruments | B12: 3 | C12: =E87 | D12: =F87
A13: Receivables | B13: 4 | C13: =E90 | D13: =F90
A14: Loans | B14: 5 | C14: =E95 | D14: =F95
A15: Investments | B15: 6 | C15: =E100 | D15: =F100
A16: Other Financial Assets | B16: 7 | C16: =E102 | D16: =F102
A17: Non-financial Assets
A18: Inventories | B18: 8 | C18: =E104 | D18: =F104
A19: Current Tax Assets (Net) | B19: 9 | C19: =E105 | D19: =F105
A20: Deferred Tax Assets (Net) | B20: 10 | C20: =E108 | D20: =F108
A21: Investment Property | B21: 11 | C21: =E112 | D21: =F112
A22: Biological Assets other than Bearer Plants | B22: 12 | C22: =E114 | D22: =F114
A23: Property, Plant and Equipment | B23: 13 | C23: =E116 | D23: =F116
A24: Capital Work-in-Progress | B24: 14 | C24: =E118 | D24: =F118
A25: Intangible Assets under Development | B25: 15 | C25: =E120 | D25: =F120
A26: Goodwill | B26: 16 | C26: =E122 | D26: =F122
A27: Other Intangible Assets | B27: 17 | C27: =E124 | D27: =F124
A28: Other Non-financial Assets | B28: 18 | C28: =E126 | D28: =F126
A29: TOTAL ASSETS | C29: =SUM(C10,C11,C12,C13,C14,C15,C16,C18,C19,C20,C21,C22,C23,C24,C25,C26,C27,C28) | D29: =SUM(D10,D11,D12,D13,D14,D15,D16,D18,D19,D20,D21,D22,D23,D24,D25,D26,D27,D28)
A30: LIABILITIES AND EQUITY
A31: Financial Liabilities
A32: Derivative Financial Instruments | B32: 3 | C32: =E87 | D32: =F87
A33: Payables | B33: 19 | C33: =E129 | D33: =F129
A34: Debt Securities | B34: 20 | C34: =E131 | D34: =F131
A35: Borrowings (other than Debt Securities) | B35: 21 | C35: =E133 | D35: =F133
A36: Deposits | B36: 22 | C36: =E135 | D36: =F135
A37: Subordinated Liabilities | B37: 23 | C37: =E137 | D37: =F137
A38: Other Financial Liabilities | B38: 24 | C38: =E139 | D38: =F139
A39: Non-financial Liabilities
A40: Current Tax Liabilities (Net) | B40: 9 | C40: =E106 | D40: =F106
A41: Provisions | B41: 25 | C41: =E141 | D41: =F141
A42: Deferred Tax Liabilities (Net) | B42: 10 | C42: =E109 | D42: =F109
A43: Other Non-financial Liabilities | B43: 26 | C43: =E143 | D43: =F143
A44: Equity
A45: Equity Share Capital | B45: 27 | C45: =E145 | D45: =F145
A46: Other Equity | B46: 28 | C46: =E147 | D46: =F147
A47: TOTAL LIABILITIES AND EQUITY | C47: =SUM(C32,C33,C34,C35,C36,C37,C38,C40,C41,C42,C43,C45,C46) | D47: =SUM(D32,D33,D34,D35,D36,D37,D38,D40,D41,D42,D43,D45,D46)
A50: Statement of Profit & Loss / Income & Expenditure / Revenue Account
A51: Particulars | B51: Note No. | C51: Current Reporting Period | D51: Previous Reporting Period
A52: REVENUE FROM OPERATIONS
A53: Interest Income | B53: 29 | C53: =E149 | D53: =F149
A54: Dividend Income | B54: 30 | C54: =E151 | D54: =F151
A55: Rental Income | B55: 31 | C55: =E153 | D55: =F153
A56: Fees and Commission Income | B56: 32 | C56: =E155 | D56: =F155
A57: Net Gain on Fair Value Changes | B57: 33 | C57: =E157 | D57: =F157
A58: Net Gain on Derecognition | B58: 34 | C58: =E159 | D58: =F159
A59: Sale of Products | B59: 35 | C59: =E161 | D59: =F161
A60: Sale of Services | B60: 36 | C60: =E163 | D60: =F163
A61: Other Income | B61: 37 | C61: =E165 | D61: =F165
A62: TOTAL INCOME | C62: =SUM(C53,C54,C55,C56,C57,C58,C59,C60,C61) | D62: =SUM(D53,D54,D55,D56,D57,D58,D59,D60,D61)
A63: EXPENSES
A64: Finance Costs | B64: 38 | C64: =E167 | D64: =F167
A65: Fees and Commission Expense | B65: 39 | C65: =E169 | D65: =F169
A66: Impairment on Financial Instruments | B66: 40 | C66: =E171 | D66: =F171
A67: Employee Benefits Expense | B67: 41 | C67: =E173 | D67: =F173
A68: Depreciation / Amortisation / Impairment | B68: 42 | C68: =E175 | D68: =F175
A69: Other Expenses | B69: 43 | C69: =E177 | D69: =F177
A70: TOTAL EXPENSES | C70: =SUM(C64,C65,C66,C67,C68,C69) | D70: =SUM(D64,D65,D66,D67,D68,D69)
A71: Profit Before Tax | C71: =C62-C70 | D71: =D62-D70
A72: Current Tax | B72: —
A73: Deferred Tax | B73: —
A74: Profit for the Period | C74: =C71-SUM(C72,C73) | D74: =D71-SUM(D72,D73)
A75: Other Comprehensive Income | B75: 44 | C75: =E179 | D75: =F179
A76: Total Comprehensive Income | C76: =C74+SUM(C75) | D76: =D74+SUM(D75)
A79: Notes / Schedules — linked source for face statements
A80: Note | B80: Note Title | C80: Statutory Line Item | D80: AAH Mapping Key | E80: Current Period | F80: Previous Period | G80: Disclosure / Remarks
A81: 1 | B81: Cash and Cash Equivalents | C81: Cash and cash equivalents | D81: CASH | E81: 0 | F81: 0
A82: 1 | B82: Cash and Cash Equivalents | C82: Total — Cash and Cash Equivalents | D82: __TOTAL__ | E82: =SUM(E81:E81) | F82: =SUM(F81:F81)
A83: 2 | B83: Bank Balance other than Cash and Cash Equivalents | C83: Other bank balances | D83: BANK_OTHER | E83: 0 | F83: 0
A84: 2 | B84: Bank Balance other than Cash and Cash Equivalents | C84: Total — Bank Balance other than Cash and Cash Equivalents | D84: __TOTAL__ | E84: =SUM(E83:E83) | F84: =SUM(F83:F83)
A85: 3 | B85: Derivative Financial Instruments | C85: Derivative financial assets | D85: DFA | E85: 0 | F85: 0
A86: 3 | B86: Derivative Financial Instruments | C86: Derivative financial liabilities | D86: DFL | E86: 0 | F86: 0
A87: 3 | B87: Derivative Financial Instruments | C87: Total — Derivative Financial Instruments | D87: __TOTAL__ | E87: =SUM(E85:E86) | F87: =SUM(F85:F86)
A88: 4 | B88: Receivables | C88: Trade receivables | D88: REC_TRADE | E88: 0 | F88: 0
A89: 4 | B89: Receivables | C89: Other receivables | D89: REC_OTHER | E89: 0 | F89: 0
A90: 4 | B90: Receivables | C90: Total — Receivables | D90: __TOTAL__ | E90: =SUM(E88:E89) | F90: =SUM(F88:F89)
A91: 5 | B91: Loans | C91: Retail loans | D91: LOAN_RETAIL | E91: 0 | F91: 0
A92: 5 | B92: Loans | C92: Corporate loans | D92: LOAN_CORP | E92: 0 | F92: 0
A93: 5 | B93: Loans | C93: Other loans | D93: LOAN_OTHER | E93: 0 | F93: 0
A94: 5 | B94: Loans | C94: Impairment allowance | D94: LOAN_ECL | E94: 0 | F94: 0
A95: 5 | B95: Loans | C95: Total — Loans | D95: __TOTAL__ | E95: =SUM(E91:E94) | F95: =SUM(F91:F94)
A96: 6 | B96: Investments | C96: Debt securities | D96: INV_DEBT | E96: 0 | F96: 0
A97: 6 | B97: Investments | C97: Equity instruments | D97: INV_EQ | E97: 0 | F97: 0
A98: 6 | B98: Investments | C98: Mutual funds | D98: INV_MF | E98: 0 | F98: 0
A99: 6 | B99: Investments | C99: Other investments | D99: INV_OTHER | E99: 0 | F99: 0
A100: 6 | B100: Investments | C100: Total — Investments | D100: __TOTAL__ | E100: =SUM(E96:E99) | F100: =SUM(F96:F99)
A101: 7 | B101: Other Financial Assets | C101: Other financial assets | D101: OFA | E101: 0 | F101: 0
A102: 7 | B102: Other Financial Assets | C102: Total — Other Financial Assets | D102: __TOTAL__ | E102: =SUM(E101:E101) | F102: =SUM(F101:F101)
A103: 8 | B103: Inventories | C103: Inventories | D103: INV | E103: 0 | F103: 0
A104: 8 | B104: Inventories | C104: Total — Inventories | D104: __TOTAL__ | E104: =SUM(E103:E103) | F104: =SUM(F103:F103)
...

Sheet NCE
A1: Non-Corporate Entity
A2: Authority: ICAI | Official source: https://www.icai.org/post/guidance-notes
A3: =IF('AAH Basic Info'!B5="","","Address: "&'AAH Basic Info'!B5) | B3: =IF('AAH Basic Info'!B6="","","PAN: "&'AAH Basic Info'!B6) | C3: =IF('AAH Basic Info'!B7="","","GSTIN: "&'AAH Basic Info'!B7) | D3: =IF('AAH Basic Info'!B27="","",'AAH Basic Info'!B27)
A4: Entity Name | B4: Current Period | C4: Previous Period | D4: Presentation Unit | E4: Standalone / Consolidated
A5: =IF('AAH Basic Info'!B3="","",'AAH Basic Info'!B3) | B5: =IF('AAH Basic Info'!B9="","",'AAH Basic Info'!B9) | C5: =IF('AAH Basic Info'!B10="","",'AAH Basic Info'!B10) | D5: =IF('AAH Basic Info'!B24="","",'AAH Basic Info'!B24) | E5: =IF('AAH Basic Info'!B25="","",'AAH Basic Info'!B25)
A6: Balance Sheet / Statement of Financial Position
A7: Particulars | B7: Note No. | C7: Current Reporting Period | D7: Previous Reporting Period
A8: OWNERS' FUNDS AND LIABILITIES
A9: Owners' Funds
A10: Owners' / Partners' Capital Account | B10: 3a | C10: =E76 | D10: =F76
A11: Owners' / Partners' Current Account | B11: 3b | C11: =E81 | D11: =F81
A12: Reserves and Surplus | B12: 4 | C12: =E86 | D12: =F86
A13: Non-current Liabilities
A14: Long-term Borrowings | B14: 5 | C14: =E87+E88 | D14: =F87+F88
A15: Deferred Tax Liabilities (Net) | B15: 6 | C15: =E93 | D15: =F93
A16: Other Long-term Liabilities | B16: 7 | C16: =E96 | D16: =F96
A17: Long-term Provisions | B17: 8 | C17: =E97 | D17: =F97
A18: Current Liabilities
A19: Short-term Borrowings | B19: 5 | C19: =E89+E90 | D19: =F89+F90
A20: Trade Payables | B20: 9 | C20: =E102 | D20: =F102
A21: Other Current Liabilities | B21: 10 | C21: =E107 | D21: =F107
A22: Short-term Provisions | B22: 8 | C22: =E98 | D22: =F98
A23: TOTAL OWNERS' FUNDS AND LIABILITIES | C23: =SUM(C10,C11,C12,C14,C15,C16,C17,C19,C20,C21,C22) | D23: =SUM(D10,D11,D12,D14,D15,D16,D17,D19,D20,D21,D22)
A24: ASSETS
A25: Non-current Assets
A26: Property, Plant and Equipment / Intangibles / CWIP | B26: 11 | C26: =E112 | D26: =F112
A27: Non-current Investments | B27: 12 | C27: =E113 | D27: =F113
A28: Deferred Tax Assets (Net) | B28: 6 | C28: =E92 | D28: =F92
A29: Long-term Loans and Advances | B29: 13 | C29: =E116 | D29: =F116
A30: Other Non-current Assets | B30: 14 | C30: =E120 | D30: =F120
A31: Current Assets
A32: Current Investments | B32: 12 | C32: =E114 | D32: =F114
A33: Inventories | B33: 15 | C33: =E126 | D33: =F126
A34: Trade Receivables | B34: 16 | C34: =E130 | D34: =F130
A35: Cash and Bank Balances | B35: 17 | C35: =E134 | D35: =F134
A36: Short-term Loans and Advances | B36: 13 | C36: =E117 | D36: =F117
A37: Other Current Assets | B37: 18 | C37: =E138 | D37: =F138
A38: TOTAL ASSETS | C38: =SUM(C26,C27,C28,C29,C30,C32,C33,C34,C35,C36,C37) | D38: =SUM(D26,D27,D28,D29,D30,D32,D33,D34,D35,D36,D37)
A41: Statement of Profit & Loss / Income & Expenditure / Revenue Account
A42: Particulars | B42: Note No. | C42: Current Reporting Period | D42: Previous Reporting Period
A43: Revenue from Operations | B43: 19 | C43: =E142 | D43: =F142
A44: Other Income | B44: 20 | C44: =E146 | D44: =F146
A45: TOTAL INCOME | C45: =SUM(C43,C44) | D45: =SUM(D43,D44)
A46: EXPENSES
A47: Cost of Materials Consumed | B47: 21 | C47: =E147 | D47: =F147
A48: Purchases of Stock-in-Trade | B48: 21 | C48: =E148 | D48: =F148
A49: Changes in Inventories | B49: 22 | C49: =E151 | D49: =F151
A50: Employee Benefits Expense | B50: 23 | C50: =E153 | D50: =F153
A51: Finance Costs | B51: 24 | C51: =E155 | D51: =F155
A52: Depreciation and Amortisation | B52: 25 | C52: =E158 | D52: =F158
A53: Other Expenses | B53: 26 | C53: =E160 | D53: =F160
A54: TOTAL EXPENSES | C54: =SUM(C47,C48,C49,C50,C51,C52,C53) | D54: =SUM(D47,D48,D49,D50,D51,D52,D53)
A55: Profit before Exceptional / Extraordinary Items, Partners' Remuneration and Tax | C55: =C45-C54 | D55: =D45-D54
A56: Exceptional Items | B56: —
A57: Profit before Extraordinary Items, Partners' Remuneration and Tax | C57: =C55-SUM(C56) | D57: =D55-SUM(D56)
A58: Extraordinary Items | B58: —
A59: Partners' Remuneration | B59: —
A60: Profit Before Tax | C60: =C57-SUM(C58,C59) | D60: =D57-SUM(D58,D59)
A61: Current Tax | B61: —
A62: Deferred Tax | B62: —
A63: Profit/(Loss) for the Year | C63: =C60-SUM(C61,C62) | D63: =D60-SUM(D61,D62)
A66: Notes / Schedules — linked source for face statements
A67: Note | B67: Note Title | C67: Statutory Line Item | D67: AAH Mapping Key | E67: Current Period | F67: Previous Period | G67: Disclosure / Remarks
A68: 1 | B68: Brief about the Entity | C68: Entity information / constitution / nature | D68: ENTITY_INFO | E68: 0 | F68: 0
A69: 1 | B69: Brief about the Entity | C69: Total — Brief about the Entity | D69: __TOTAL__ | E69: =SUM(E68:E68) | F69: =SUM(F68:F68)
A70: 2 | B70: Summary of Significant Accounting Policies | C70: Accounting policies disclosure | D70: POLICIES | E70: 0 | F70: 0
A71: 2 | B71: Summary of Significant Accounting Policies | C71: Total — Summary of Significant Accounting Policies | D71: __TOTAL__ | E71: =SUM(E70:E70) | F71: =SUM(F70:F70)
A72: 3a | B72: Owners' / Partners' Capital Account | C72: Opening capital | D72: CAP_OPEN | E72: 0 | F72: 0
A73: 3a | B73: Owners' / Partners' Capital Account | C73: Capital introduced | D73: CAP_ADD | E73: 0 | F73: 0
A74: 3a | B74: Owners' / Partners' Capital Account | C74: Withdrawals / drawings | D74: CAP_DRAW | E74: 0 | F74: 0
A75: 3a | B75: Owners' / Partners' Capital Account | C75: Share of profit / loss | D75: CAP_SHAREPL | E75: 0 | F75: 0
A76: 3a | B76: Owners' / Partners' Capital Account | C76: Total — Owners' / Partners' Capital Account | D76: __TOTAL__ | E76: =SUM(E72:E75) | F76: =SUM(F72:F75)
A77: 3b | B77: Owners' / Partners' Current Account | C77: Opening current account | D77: CURR_OPEN | E77: 0 | F77: 0
A78: 3b | B78: Owners' / Partners' Current Account | C78: Credits | D78: CURR_CR | E78: 0 | F78: 0
A79: 3b | B79: Owners' / Partners' Current Account | C79: Debits / drawings | D79: CURR_DR | E79: 0 | F79: 0
A80: 3b | B80: Owners' / Partners' Current Account | C80: Share of profit / loss | D80: CURR_SHAREPL | E80: 0 | F80: 0
A81: 3b | B81: Owners' / Partners' Current Account | C81: Total — Owners' / Partners' Current Account | D81: __TOTAL__ | E81: =SUM(E77:E80) | F81: =SUM(F77:F80)
A82: 4 | B82: Reserves and Surplus | C82: Capital reserve | D82: RES_CAP | E82: 0 | F82: 0
A83: 4 | B83: Reserves and Surplus | C83: Revaluation reserve | D83: RES_REVAL | E83: 0 | F83: 0
A84: 4 | B84: Reserves and Surplus | C84: Other reserves | D84: RES_OTHER | E84: 0 | F84: 0
A85: 4 | B85: Reserves and Surplus | C85: Undistributed surplus | D85: RES_SURPLUS | E85: 0 | F85: 0
A86: 4 | B86: Reserves and Surplus | C86: Total — Reserves and Surplus | D86: __TOTAL__ | E86: =SUM(E82:E85) | F86: =SUM(F82:F85)
A87: 5 | B87: Borrowings | C87: Long-term secured | D87: BORR_LT_SEC | E87: 0 | F87: 0
A88: 5 | B88: Borrowings | C88: Long-term unsecured | D88: BORR_LT_UNSEC | E88: 0 | F88: 0
A89: 5 | B89: Borrowings | C89: Short-term secured | D89: BORR_ST_SEC | E89: 0 | F89: 0
A90: 5 | B90: Borrowings | C90: Short-term unsecured | D90: BORR_ST_UNSEC | E90: 0 | F90: 0
A91: 5 | B91: Borrowings | C91: Total — Borrowings | D91: __TOTAL__ | E91: =SUM(E87:E90) | F91: =SUM(F87:F90)
A92: 6 | B92: Deferred Tax | C92: Deferred tax asset | D92: DTA | E92: 0 | F92: 0
A93: 6 | B93: Deferred Tax | C93: Deferred tax liability | D93: DTL | E93: 0 | F93: 0
A94: 6 | B94: Deferred Tax | C94: Total — Deferred Tax | D94: __TOTAL__ | E94: =SUM(E92:E93) | F94: =SUM(F92:F93)
A95: 7 | B95: Other Long-term Liabilities | C95: Other long-term liabilities | D95: OLTL | E95: 0 | F95: 0
A96: 7 | B96: Other Long-term Liabilities | C96: Total — Other Long-term Liabilities | D96: __TOTAL__ | E96: =SUM(E95:E95) | F96: =SUM(F95:F95)
A97: 8 | B97: Provisions | C97: Long-term provisions | D97: PROV_LT | E97: 0 | F97: 0
A98: 8 | B98: Provisions | C98: Short-term provisions | D98: PROV_ST | E98: 0 | F98: 0
A99: 8 | B99: Provisions | C99: Total — Provisions | D99: __TOTAL__ | E99: =SUM(E97:E98) | F99: =SUM(F97:F98)
A100: 9 | B100: Trade Payables | C100: MSME dues | D100: TP_MSME | E100: 0 | F100: 0
A101: 9 | B101: Trade Payables | C101: Other trade payables | D101: TP_OTHER | E101: 0 | F101: 0
A102: 9 | B102: Trade Payables | C102: Total — Trade Payables | D102: __TOTAL__ | E102: =SUM(E100:E101) | F102: =SUM(F100:F101)
A103: 10 | B103: Other Current Liabilities | C103: Statutory dues | D103: OCL_STAT | E103: 0 | F103: 0
A104: 10 | B104: Other Current Liabilities | C104: Accrued expenses | D104: OCL_ACCR | E104: 0 | F104: 0
...

Sheet LLP
A1: Limited Liability Partnership
A2: Authority: ICAI + MCA | Official source: https://www.icai.org/post/guidance-notes
A3: =IF('AAH Basic Info'!B5="","","Address: "&'AAH Basic Info'!B5) | B3: =IF('AAH Basic Info'!B6="","","PAN: "&'AAH Basic Info'!B6) | C3: =IF('AAH Basic Info'!B7="","","GSTIN: "&'AAH Basic Info'!B7) | D3: =IF('AAH Basic Info'!B27="","",'AAH Basic Info'!B27)
A4: Entity Name | B4: Current Period | C4: Previous Period | D4: Presentation Unit | E4: Standalone / Consolidated
A5: =IF('AAH Basic Info'!B3="","",'AAH Basic Info'!B3) | B5: =IF('AAH Basic Info'!B9="","",'AAH Basic Info'!B9) | C5: =IF('AAH Basic Info'!B10="","",'AAH Basic Info'!B10) | D5: =IF('AAH Basic Info'!B24="","",'AAH Basic Info'!B24) | E5: =IF('AAH Basic Info'!B25="","",'AAH Basic Info'!B25)
A6: Balance Sheet / Statement of Financial Position
A7: Particulars | B7: Note No. | C7: Current Reporting Period | D7: Previous Reporting Period
A8: PARTNERS' FUNDS AND LIABILITIES
A9: Partners' Contribution | B9: 3 | C9: =E68 | D9: =F68
A10: Partners' Current Accounts | B10: 4 | C10: =E70 | D10: =F70
A11: Reserves and Surplus | B11: 5 | C11: =E72 | D11: =F72
A12: Non-current Liabilities
A13: Long-term Borrowings | B13: 6 | C13: =E73 | D13: =F73
A14: Deferred Tax Liabilities (Net) | B14: 7 | C14: =E77 | D14: =F77
A15: Other Long-term Liabilities | B15: 8 | C15: =E79 | D15: =F79
A16: Long-term Provisions | B16: 9 | C16: =E82 | D16: =F82
A17: Current Liabilities
A18: Short-term Borrowings | B18: 6 | C18: =E74 | D18: =F74
A19: Trade Payables | B19: 10 | C19: =E87 | D19: =F87
A20: Other Current Liabilities | B20: 8 | C20: =E80 | D20: =F80
A21: Short-term Provisions | B21: 9 | C21: =E83 | D21: =F83
A22: TOTAL PARTNERS' FUNDS AND LIABILITIES | C22: =SUM(C9,C10,C11,C13,C14,C15,C16,C18,C19,C20,C21) | D22: =SUM(D9,D10,D11,D13,D14,D15,D16,D18,D19,D20,D21)
A23: ASSETS
A24: Non-current Assets
A25: PPE / Intangibles / CWIP | B25: 11 | C25: =E92 | D25: =F92
A26: Non-current Investments | B26: 12 | C26: =E93 | D26: =F93
A27: Deferred Tax Assets (Net) | B27: 7 | C27: =E76 | D27: =F76
A28: Long-term Loans and Advances | B28: 13 | C28: =E96 | D28: =F96
A29: Other Non-current Assets | B29: 14 | C29: =E100 | D29: =F100
A30: Current Assets
A31: Current Investments | B31: 12 | C31: =E94 | D31: =F94
A32: Inventories | B32: 15 | C32: =E102 | D32: =F102
A33: Trade Receivables | B33: 16 | C33: =E104 | D33: =F104
A34: Cash and Bank Balances | B34: 17 | C34: =E106 | D34: =F106
A35: Short-term Loans and Advances | B35: 13 | C35: =E97 | D35: =F97
A36: Other Current Assets | B36: 18 | C36: =E108 | D36: =F108
A37: TOTAL ASSETS | C37: =SUM(C25,C26,C27,C28,C29,C31,C32,C33,C34,C35,C36) | D37: =SUM(D25,D26,D27,D28,D29,D31,D32,D33,D34,D35,D36)
A40: Statement of Profit & Loss / Income & Expenditure / Revenue Account
A41: Particulars | B41: Note No. | C41: Current Reporting Period | D41: Previous Reporting Period
A42: Revenue from Operations | B42: 19 | C42: =E110 | D42: =F110
A43: Other Income | B43: 20 | C43: =E112 | D43: =F112
A44: TOTAL INCOME | C44: =SUM(C42,C43) | D44: =SUM(D42,D43)
A45: EXPENSES
A46: Materials / Purchases | B46: 21 | C46: =E114 | D46: =F114
A47: Changes in Inventories | B47: 22 | C47: =E116 | D47: =F116
A48: Employee Benefits | B48: 23 | C48: =E118 | D48: =F118
A49: Finance Costs | B49: 24 | C49: =E120 | D49: =F120
A50: Depreciation and Amortisation | B50: 25 | C50: =E122 | D50: =F122
A51: Other Expenses | B51: 26 | C51: =E124 | D51: =F124
A52: Partners' Remuneration / Interest | B52: —
A53: TOTAL EXPENSES | C53: =SUM(C46,C47,C48,C49,C50,C51) | D53: =SUM(D46,D47,D48,D49,D50,D51)
A54: Profit Before Tax | C54: =C44-C53 | D54: =D44-D53
A55: Current Tax | B55: —
A56: Deferred Tax | B56: —
A57: Profit/(Loss) for the Year | C57: =C54-SUM(C55,C56) | D57: =D54-SUM(D55,D56)
A60: Notes / Schedules — linked source for face statements
A61: Note | B61: Note Title | C61: Statutory Line Item | D61: AAH Mapping Key | E61: Current Period | F61: Previous Period | G61: Disclosure / Remarks
A62: 1 | B62: Brief about LLP | C62: LLP information | D62: LLP_INFO | E62: 0 | F62: 0
A63: 1 | B63: Brief about LLP | C63: Total — Brief about LLP | D63: __TOTAL__ | E63: =SUM(E62:E62) | F63: =SUM(F62:F62)
A64: 2 | B64: Significant Accounting Policies | C64: Accounting policies | D64: POLICIES | E64: 0 | F64: 0
A65: 2 | B65: Significant Accounting Policies | C65: Total — Significant Accounting Policies | D65: __TOTAL__ | E65: =SUM(E64:E64) | F65: =SUM(F64:F64)
A66: 3 | B66: Partners' Contribution | C66: Fixed contribution | D66: PC_FIXED | E66: 0 | F66: 0
A67: 3 | B67: Partners' Contribution | C67: Other contribution | D67: PC_OTHER | E67: 0 | F67: 0
A68: 3 | B68: Partners' Contribution | C68: Total — Partners' Contribution | D68: __TOTAL__ | E68: =SUM(E66:E67) | F68: =SUM(F66:F67)
A69: 4 | B69: Partners' Current Accounts | C69: Partners' current accounts | D69: PCURR | E69: 0 | F69: 0
A70: 4 | B70: Partners' Current Accounts | C70: Total — Partners' Current Accounts | D70: __TOTAL__ | E70: =SUM(E69:E69) | F70: =SUM(F69:F69)
A71: 5 | B71: Reserves and Surplus | C71: Reserves and surplus | D71: RES | E71: 0 | F71: 0
A72: 5 | B72: Reserves and Surplus | C72: Total — Reserves and Surplus | D72: __TOTAL__ | E72: =SUM(E71:E71) | F72: =SUM(F71:F71)
A73: 6 | B73: Borrowings | C73: Long-term borrowings | D73: BORR_LT | E73: 0 | F73: 0
A74: 6 | B74: Borrowings | C74: Short-term borrowings | D74: BORR_ST | E74: 0 | F74: 0
A75: 6 | B75: Borrowings | C75: Total — Borrowings | D75: __TOTAL__ | E75: =SUM(E73:E74) | F75: =SUM(F73:F74)
A76: 7 | B76: Deferred Tax | C76: DTA | D76: DTA | E76: 0 | F76: 0
A77: 7 | B77: Deferred Tax | C77: DTL | D77: DTL | E77: 0 | F77: 0
A78: 7 | B78: Deferred Tax | C78: Total — Deferred Tax | D78: __TOTAL__ | E78: =SUM(E76:E77) | F78: =SUM(F76:F77)
A79: 8 | B79: Other Liabilities | C79: Long-term liabilities | D79: OL_LT | E79: 0 | F79: 0
A80: 8 | B80: Other Liabilities | C80: Current liabilities | D80: OL_CURR | E80: 0 | F80: 0
A81: 8 | B81: Other Liabilities | C81: Total — Other Liabilities | D81: __TOTAL__ | E81: =SUM(E79:E80) | F81: =SUM(F79:F80)
A82: 9 | B82: Provisions | C82: Long-term provisions | D82: PROV_LT | E82: 0 | F82: 0
A83: 9 | B83: Provisions | C83: Short-term provisions | D83: PROV_ST | E83: 0 | F83: 0
A84: 9 | B84: Provisions | C84: Total — Provisions | D84: __TOTAL__ | E84: =SUM(E82:E83) | F84: =SUM(F82:F83)
A85: 10 | B85: Trade Payables | C85: MSME trade payables | D85: TP_MSME | E85: 0 | F85: 0
A86: 10 | B86: Trade Payables | C86: Other trade payables | D86: TP_OTHER | E86: 0 | F86: 0
A87: 10 | B87: Trade Payables | C87: Total — Trade Payables | D87: __TOTAL__ | E87: =SUM(E85:E86) | F87: =SUM(F85:F86)
A88: 11 | B88: PPE / Intangibles / CWIP | C88: PPE | D88: PPE | E88: 0 | F88: 0
A89: 11 | B89: PPE / Intangibles / CWIP | C89: Intangibles | D89: INTANG | E89: 0 | F89: 0
A90: 11 | B90: PPE / Intangibles / CWIP | C90: CWIP | D90: CWIP | E90: 0 | F90: 0
A91: 11 | B91: PPE / Intangibles / CWIP | C91: IAUD | D91: IAUD | E91: 0 | F91: 0
A92: 11 | B92: PPE / Intangibles / CWIP | C92: Total — PPE / Intangibles / CWIP | D92: __TOTAL__ | E92: =SUM(E88:E91) | F92: =SUM(F88:F91)
A93: 12 | B93: Investments | C93: Non-current investments | D93: INV_NC | E93: 0 | F93: 0
A94: 12 | B94: Investments | C94: Current investments | D94: INV_CURR | E94: 0 | F94: 0
A95: 12 | B95: Investments | C95: Total — Investments | D95: __TOTAL__ | E95: =SUM(E93:E94) | F95: =SUM(F93:F94)
A96: 13 | B96: Loans and Advances | C96: Long-term loans / advances | D96: LA_LT | E96: 0 | F96: 0
A97: 13 | B97: Loans and Advances | C97: Short-term loans / advances | D97: LA_ST | E97: 0 | F97: 0
A98: 13 | B98: Loans and Advances | C98: Total — Loans and Advances | D98: __TOTAL__ | E98: =SUM(E96:E97) | F98: =SUM(F96:F97)
A99: 14 | B99: Other Non-current Assets | C99: Other non-current assets | D99: ONCA | E99: 0 | F99: 0
A100: 14 | B100: Other Non-current Assets | C100: Total — Other Non-current Assets | D100: __TOTAL__ | E100: =SUM(E99:E99) | F100: =SUM(F99:F99)
A101: 15 | B101: Inventories | C101: Inventories | D101: INV | E101: 0 | F101: 0
A102: 15 | B102: Inventories | C102: Total — Inventories | D102: __TOTAL__ | E102: =SUM(E101:E101) | F102: =SUM(F101:F101)
A103: 16 | B103: Trade Receivables | C103: Trade receivables | D103: TR | E103: 0 | F103: 0
A104: 16 | B104: Trade Receivables | C104: Total — Trade Receivables | D104: __TOTAL__ | E104: =SUM(E103:E103) | F104: =SUM(F103:F103)
...

Sheet NPO
A1: Not-for-Profit Organisation
A2: Authority: ICAI / governing statute | Official source: https://www.icai.org/post/technical-guides-and-other-materials
A3: =IF('AAH Basic Info'!B5="","","Address: "&'AAH Basic Info'!B5) | B3: =IF('AAH Basic Info'!B6="","","PAN: "&'AAH Basic Info'!B6) | C3: =IF('AAH Basic Info'!B7="","","GSTIN: "&'AAH Basic Info'!B7) | D3: =IF('AAH Basic Info'!B27="","",'AAH Basic Info'!B27)
A4: Entity Name | B4: Current Period | C4: Previous Period | D4: Presentation Unit | E4: Standalone / Consolidated
A5: =IF('AAH Basic Info'!B3="","",'AAH Basic Info'!B3) | B5: =IF('AAH Basic Info'!B9="","",'AAH Basic Info'!B9) | C5: =IF('AAH Basic Info'!B10="","",'AAH Basic Info'!B10) | D5: =IF('AAH Basic Info'!B24="","",'AAH Basic Info'!B24) | E5: =IF('AAH Basic Info'!B25="","",'AAH Basic Info'!B25)
A6: Balance Sheet / Statement of Financial Position
A7: Particulars | B7: Note No. | C7: Current Reporting Period | D7: Previous Reporting Period
A8: FUNDS AND LIABILITIES
A9: Corpus / Capital Fund | B9: 1 | C9: =E46 | D9: =F46
A10: Restricted / Earmarked Funds | B10: 2 | C10: =E48 | D10: =F48
A11: Unrestricted / General Fund | B11: 3 | C11: =E50 | D11: =F50
A12: Secured / Unsecured Loans | B12: 4 | C12: =E53 | D12: =F53
A13: Deferred Credit Liabilities | B13: 5 | C13: =E55 | D13: =F55
A14: Current Liabilities and Provisions | B14: 6 | C14: =E58 | D14: =F58
A15: TOTAL FUNDS AND LIABILITIES | C15: =SUM(C9,C10,C11,C12,C13,C14) | D15: =SUM(D9,D10,D11,D12,D13,D14)
A16: ASSETS
A17: Fixed Assets / PPE | B17: 7 | C17: =E60 | D17: =F60
A18: Investments - Earmarked / Endowment Funds | B18: 8 | C18: =E62 | D18: =F62
A19: Other Investments | B19: 9 | C19: =E64 | D19: =F64
A20: Current Assets, Loans and Advances | B20: 10 | C20: =E67 | D20: =F67
A21: TOTAL ASSETS | C21: =SUM(C17,C18,C19,C20) | D21: =SUM(D17,D18,D19,D20)
A24: Income and Expenditure Account
A25: Particulars | B25: Note No. | C25: Current Reporting Period | D25: Previous Reporting Period
A26: INCOME
A27: Grants / Donations / Contributions | B27: 11 | C27: =E70 | D27: =F70
A28: Membership / Subscription Income | B28: 12 | C28: =E72 | D28: =F72
A29: Income from Investments | B29: 13 | C29: =E74 | D29: =F74
A30: Other Income | B30: 14 | C30: =E76 | D30: =F76
A31: TOTAL INCOME | C31: =SUM(C27,C28,C29,C30) | D31: =SUM(D27,D28,D29,D30)
A32: EXPENDITURE
A33: Programme / Project Expenses | B33: 15 | C33: =E78 | D33: =F78
A34: Employee Costs | B34: 16 | C34: =E80 | D34: =F80
A35: Administrative Expenses | B35: 17 | C35: =E82 | D35: =F82
A36: Finance Costs | B36: 18 | C36: =E84 | D36: =F84
A37: Depreciation / Amortisation | B37: 19 | C37: =E86 | D37: =F86
A38: Other Expenses | B38: 20 | C38: =E88 | D38: =F88
A39: TOTAL EXPENDITURE | C39: =SUM(C33,C34,C35,C36,C37,C38) | D39: =SUM(D33,D34,D35,D36,D37,D38)
A40: Surplus / (Deficit) for the Year | C40: =C31-C39 | D40: =D31-D39
A43: Notes / Schedules — linked source for face statements
A44: Note | B44: Note Title | C44: Statutory Line Item | D44: AAH Mapping Key | E44: Current Period | F44: Previous Period | G44: Disclosure / Remarks
A45: 1 | B45: Corpus / Capital Fund | C45: Corpus fund | D45: FUND_CORPUS | E45: 0 | F45: 0
A46: 1 | B46: Corpus / Capital Fund | C46: Total — Corpus / Capital Fund | D46: __TOTAL__ | E46: =SUM(E45:E45) | F46: =SUM(F45:F45)
A47: 2 | B47: Restricted / Earmarked Funds | C47: Restricted / earmarked funds | D47: FUND_RESTRICT | E47: 0 | F47: 0
A48: 2 | B48: Restricted / Earmarked Funds | C48: Total — Restricted / Earmarked Funds | D48: __TOTAL__ | E48: =SUM(E47:E47) | F48: =SUM(F47:F47)
A49: 3 | B49: Unrestricted / General Fund | C49: General fund | D49: FUND_GENERAL | E49: 0 | F49: 0
A50: 3 | B50: Unrestricted / General Fund | C50: Total — Unrestricted / General Fund | D50: __TOTAL__ | E50: =SUM(E49:E49) | F50: =SUM(F49:F49)
A51: 4 | B51: Loans | C51: Secured loans | D51: LOAN_SEC | E51: 0 | F51: 0
A52: 4 | B52: Loans | C52: Unsecured loans | D52: LOAN_UNSEC | E52: 0 | F52: 0
A53: 4 | B53: Loans | C53: Total — Loans | D53: __TOTAL__ | E53: =SUM(E51:E52) | F53: =SUM(F51:F52)
A54: 5 | B54: Deferred Credit Liabilities | C54: Deferred credit liabilities | D54: DCL | E54: 0 | F54: 0
A55: 5 | B55: Deferred Credit Liabilities | C55: Total — Deferred Credit Liabilities | D55: __TOTAL__ | E55: =SUM(E54:E54) | F55: =SUM(F54:F54)
A56: 6 | B56: Current Liabilities and Provisions | C56: Current liabilities | D56: CL | E56: 0 | F56: 0
A57: 6 | B57: Current Liabilities and Provisions | C57: Provisions | D57: PROV | E57: 0 | F57: 0
A58: 6 | B58: Current Liabilities and Provisions | C58: Total — Current Liabilities and Provisions | D58: __TOTAL__ | E58: =SUM(E56:E57) | F58: =SUM(F56:F57)
A59: 7 | B59: Fixed Assets / PPE | C59: Fixed assets / PPE | D59: PPE | E59: 0 | F59: 0
A60: 7 | B60: Fixed Assets / PPE | C60: Total — Fixed Assets / PPE | D60: __TOTAL__ | E60: =SUM(E59:E59) | F60: =SUM(F59:F59)
A61: 8 | B61: Investments - Earmarked / Endowment Funds | C61: Earmarked / endowment investments | D61: INV_EARMARK | E61: 0 | F61: 0
A62: 8 | B62: Investments - Earmarked / Endowment Funds | C62: Total — Investments - Earmarked / Endowment Funds | D62: __TOTAL__ | E62: =SUM(E61:E61) | F62: =SUM(F61:F61)
A63: 9 | B63: Other Investments | C63: Other investments | D63: INV_OTHER | E63: 0 | F63: 0
A64: 9 | B64: Other Investments | C64: Total — Other Investments | D64: __TOTAL__ | E64: =SUM(E63:E63) | F64: =SUM(F63:F63)
A65: 10 | B65: Current Assets, Loans and Advances | C65: Current assets | D65: CA | E65: 0 | F65: 0
A66: 10 | B66: Current Assets, Loans and Advances | C66: Loans and advances | D66: LA | E66: 0 | F66: 0
A67: 10 | B67: Current Assets, Loans and Advances | C67: Total — Current Assets, Loans and Advances | D67: __TOTAL__ | E67: =SUM(E65:E66) | F67: =SUM(F65:F66)
A68: 11 | B68: Grants / Donations / Contributions | C68: Grants | D68: INC_GRANT | E68: 0 | F68: 0
A69: 11 | B69: Grants / Donations / Contributions | C69: Donations / contributions | D69: INC_DON | E69: 0 | F69: 0
A70: 11 | B70: Grants / Donations / Contributions | C70: Total — Grants / Donations / Contributions | D70: __TOTAL__ | E70: =SUM(E68:E69) | F70: =SUM(F68:F69)
A71: 12 | B71: Membership / Subscription Income | C71: Membership / subscription | D71: INC_SUB | E71: 0 | F71: 0
A72: 12 | B72: Membership / Subscription Income | C72: Total — Membership / Subscription Income | D72: __TOTAL__ | E72: =SUM(E71:E71) | F72: =SUM(F71:F71)
A73: 13 | B73: Income from Investments | C73: Investment income | D73: INC_INV | E73: 0 | F73: 0
A74: 13 | B74: Income from Investments | C74: Total — Income from Investments | D74: __TOTAL__ | E74: =SUM(E73:E73) | F74: =SUM(F73:F73)
A75: 14 | B75: Other Income | C75: Other income | D75: INC_OTHER | E75: 0 | F75: 0
A76: 14 | B76: Other Income | C76: Total — Other Income | D76: __TOTAL__ | E76: =SUM(E75:E75) | F76: =SUM(F75:F75)
A77: 15 | B77: Programme / Project Expenses | C77: Programme / project expenses | D77: EXP_PROG | E77: 0 | F77: 0
A78: 15 | B78: Programme / Project Expenses | C78: Total — Programme / Project Expenses | D78: __TOTAL__ | E78: =SUM(E77:E77) | F78: =SUM(F77:F77)
A79: 16 | B79: Employee Costs | C79: Employee costs | D79: EXP_EMP | E79: 0 | F79: 0
A80: 16 | B80: Employee Costs | C80: Total — Employee Costs | D80: __TOTAL__ | E80: =SUM(E79:E79) | F80: =SUM(F79:F79)
A81: 17 | B81: Administrative Expenses | C81: Administrative expenses | D81: EXP_ADMIN | E81: 0 | F81: 0
A82: 17 | B82: Administrative Expenses | C82: Total — Administrative Expenses | D82: __TOTAL__ | E82: =SUM(E81:E81) | F82: =SUM(F81:F81)
A83: 18 | B83: Finance Costs | C83: Finance costs | D83: EXP_FIN | E83: 0 | F83: 0
A84: 18 | B84: Finance Costs | C84: Total — Finance Costs | D84: __TOTAL__ | E84: =SUM(E83:E83) | F84: =SUM(F83:F83)
A85: 19 | B85: Depreciation / Amortisation | C85: Depreciation / amortisation | D85: EXP_DEPAM | E85: 0 | F85: 0
A86: 19 | B86: Depreciation / Amortisation | C86: Total — Depreciation / Amortisation | D86: __TOTAL__ | E86: =SUM(E85:E85) | F86: =SUM(F85:F85)
A87: 20 | B87: Other Expenses | C87: Other expenses | D87: EXP_OTHER | E87: 0 | F87: 0
A88: 20 | B88: Other Expenses | C88: Total — Other Expenses | D88: __TOTAL__ | E88: =SUM(E87:E87) | F88: =SUM(F87:F87)
A91: Validation
A92: Check | B92: Current Period | C92: Previous Period | D92: Result
A93: Balance Sheet difference | B93: =C21-C15 | C93: =D21-D15 | D93: =IF(AND(ABS(B93)<1,ABS(C93)<1),"PASS","CHECK")
A94: Notes / disclosures | B94: Review | C94: Review | D94: Review
A95: Profile readiness | D95: =IF(D93="PASS","READY FOR REVIEW","NOT READY")
A99: Signatures / Certification
A100: Entity Signatory | B100: ='AAH Basic Info'!B13 | C100: Designation | D100: ='AAH Basic Info'!B14 | E100: DIN | F100: ='AAH Basic Info'!B15
A101: Signing Date | B101: ='AAH Basic Info'!B16 | C101: Place | D101: ='AAH Basic Info'!B17
A102: Audit Firm | B102: ='AAH Basic Info'!B18 | C102: FRN | D102: ='AAH Basic Info'!B19
A103: Signing CA | B103: ='AAH Basic Info'!B20 | C103: Designation | D103: ='AAH Basic Info'!B21 | E103: Membership No. | F103: ='AAH Basic Info'!B22
A104: Audit Place | B104: ='AAH Basic Info'!B23 | C104: Signing Date | D104: ='AAH Basic Info'!B30

Sheet BANK
A1: Banking Company
A2: Authority: RBI / Banking Regulation Act | Official source: https://www.indiacode.nic.in/bitstream/123456789/1885/1/A194910.pdf
A3: =IF('AAH Basic Info'!B5="","","Address: "&'AAH Basic Info'!B5) | B3: =IF('AAH Basic Info'!B6="","","PAN: "&'AAH Basic Info'!B6) | C3: =IF('AAH Basic Info'!B7="","","GSTIN: "&'AAH Basic Info'!B7) | D3: =IF('AAH Basic Info'!B27="","",'AAH Basic Info'!B27)
A4: Entity Name | B4: Current Period | C4: Previous Period | D4: Presentation Unit | E4: Standalone / Consolidated
A5: =IF('AAH Basic Info'!B3="","",'AAH Basic Info'!B3) | B5: =IF('AAH Basic Info'!B9="","",'AAH Basic Info'!B9) | C5: =IF('AAH Basic Info'!B10="","",'AAH Basic Info'!B10) | D5: =IF('AAH Basic Info'!B24="","",'AAH Basic Info'!B24) | E5: =IF('AAH Basic Info'!B25="","",'AAH Basic Info'!B25)
A6: Form A — Balance Sheet
A7: Particulars | B7: Schedule | C7: Current Reporting Period | D7: Previous Reporting Period
A8: CAPITAL AND LIABILITIES
A9: Capital | B9: 1 | C9: =E47 | D9: =F47
A10: Reserves and Surplus | B10: 2 | C10: =E53 | D10: =F53
A11: Deposits | B11: 3 | C11: =E57 | D11: =F57
A12: Borrowings | B12: 4 | C12: =E60 | D12: =F60
A13: Other Liabilities and Provisions | B13: 5 | C13: =E66 | D13: =F66
A14: TOTAL CAPITAL AND LIABILITIES | C14: =SUM(C9,C10,C11,C12,C13) | D14: =SUM(D9,D10,D11,D12,D13)
A15: ASSETS
A16: Cash and Balances with Reserve Bank of India | B16: 6 | C16: =E69 | D16: =F69
A17: Balances with Banks and Money at Call and Short Notice | B17: 7 | C17: =E73 | D17: =F73
A18: Investments | B18: 8 | C18: =E80 | D18: =F80
A19: Advances | B19: 9 | C19: =E85 | D19: =F85
A20: Fixed Assets | B20: 10 | C20: =E89 | D20: =F89
A21: Other Assets | B21: 11 | C21: =E96 | D21: =F96
A22: TOTAL ASSETS | C22: =SUM(C16,C17,C18,C19,C20,C21) | D22: =SUM(D16,D17,D18,D19,D20,D21)
A23: CONTINGENT LIABILITIES
A24: Contingent Liabilities | B24: 12 | C24: =E103 | D24: =F103
A27: Form B — Profit and Loss Account
A28: Particulars | B28: Schedule | C28: Current Reporting Period | D28: Previous Reporting Period
A29: INCOME
A30: Interest Earned | B30: 13 | C30: =E108 | D30: =F108
A31: Other Income | B31: 14 | C31: =E114 | D31: =F114
A32: TOTAL INCOME | C32: =SUM(C30,C31) | D32: =SUM(D30,D31)
A33: EXPENDITURE
A34: Interest Expended | B34: 15 | C34: =E118 | D34: =F118
A35: Operating Expenses | B35: 16 | C35: =E131 | D35: =F131
A36: Provisions and Contingencies | B36: —
A37: TOTAL EXPENDITURE | C37: =SUM(C34,C35) | D37: =SUM(D34,D35)
A38: Profit / (Loss) before Tax | C38: =C32-C37 | D38: =D32-D37
A39: Tax | B39: —
A40: Net Profit / (Loss) | C40: =C38-SUM(C39) | D40: =D38-SUM(D39)
A43: Notes / Schedules — linked source for face statements
A44: Note | B44: Note Title | C44: Statutory Line Item | D44: AAH Mapping Key | E44: Current Period | F44: Previous Period | G44: Disclosure / Remarks
A45: 1 | B45: Capital | C45: Authorised capital | D45: BANK_CAP_AUTH | E45: 0 | F45: 0
A46: 1 | B46: Capital | C46: Issued / subscribed / paid-up capital | D46: BANK_CAP_PAID | E46: 0 | F46: 0
A47: 1 | B47: Capital | C47: Total — Capital | D47: __TOTAL__ | E47: =SUM(E45:E46) | F47: =SUM(F45:F46)
A48: 2 | B48: Reserves and Surplus | C48: Statutory reserve | D48: BANK_RES_STAT | E48: 0 | F48: 0
A49: 2 | B49: Reserves and Surplus | C49: Capital reserve | D49: BANK_RES_CAP | E49: 0 | F49: 0
A50: 2 | B50: Reserves and Surplus | C50: Share premium | D50: BANK_RES_SP | E50: 0 | F50: 0
A51: 2 | B51: Reserves and Surplus | C51: Revenue / other reserves | D51: BANK_RES_OTHER | E51: 0 | F51: 0
A52: 2 | B52: Reserves and Surplus | C52: Balance in P&L | D52: BANK_RES_PL | E52: 0 | F52: 0
A53: 2 | B53: Reserves and Surplus | C53: Total — Reserves and Surplus | D53: __TOTAL__ | E53: =SUM(E48:E52) | F53: =SUM(F48:F52)
A54: 3 | B54: Deposits | C54: Demand deposits | D54: BANK_DEP_DEM | E54: 0 | F54: 0
A55: 3 | B55: Deposits | C55: Savings bank deposits | D55: BANK_DEP_SAV | E55: 0 | F55: 0
A56: 3 | B56: Deposits | C56: Term deposits | D56: BANK_DEP_TERM | E56: 0 | F56: 0
A57: 3 | B57: Deposits | C57: Total — Deposits | D57: __TOTAL__ | E57: =SUM(E54:E56) | F57: =SUM(F54:F56)
A58: 4 | B58: Borrowings | C58: Borrowings in India | D58: BANK_BORR_IN | E58: 0 | F58: 0
A59: 4 | B59: Borrowings | C59: Borrowings outside India | D59: BANK_BORR_OUT | E59: 0 | F59: 0
A60: 4 | B60: Borrowings | C60: Total — Borrowings | D60: __TOTAL__ | E60: =SUM(E58:E59) | F60: =SUM(F58:F59)
A61: 5 | B61: Other Liabilities and Provisions | C61: Bills payable | D61: BANK_OL_BILLS | E61: 0 | F61: 0
A62: 5 | B62: Other Liabilities and Provisions | C62: Inter-office adjustments | D62: BANK_OL_IO | E62: 0 | F62: 0
A63: 5 | B63: Other Liabilities and Provisions | C63: Interest accrued | D63: BANK_OL_INT | E63: 0 | F63: 0
A64: 5 | B64: Other Liabilities and Provisions | C64: Other liabilities | D64: BANK_OL_OTHER | E64: 0 | F64: 0
A65: 5 | B65: Other Liabilities and Provisions | C65: Provisions | D65: BANK_OL_PROV | E65: 0 | F65: 0
A66: 5 | B66: Other Liabilities and Provisions | C66: Total — Other Liabilities and Provisions | D66: __TOTAL__ | E66: =SUM(E61:E65) | F66: =SUM(F61:F65)
A67: 6 | B67: Cash and Balances with RBI | C67: Cash in hand | D67: BANK_CASH | E67: 0 | F67: 0
A68: 6 | B68: Cash and Balances with RBI | C68: Balances with RBI | D68: BANK_RBI | E68: 0 | F68: 0
A69: 6 | B69: Cash and Balances with RBI | C69: Total — Cash and Balances with RBI | D69: __TOTAL__ | E69: =SUM(E67:E68) | F69: =SUM(F67:F68)
A70: 7 | B70: Balances with Banks and Money at Call / Short Notice | C70: Balances with banks in India | D70: BANK_BAL_IN | E70: 0 | F70: 0
A71: 7 | B71: Balances with Banks and Money at Call / Short Notice | C71: Money at call / short notice | D71: BANK_CALL | E71: 0 | F71: 0
A72: 7 | B72: Balances with Banks and Money at Call / Short Notice | C72: Balances outside India | D72: BANK_BAL_OUT | E72: 0 | F72: 0
A73: 7 | B73: Balances with Banks and Money at Call / Short Notice | C73: Total — Balances with Banks and Money at Call / Short Notice | D73: __TOTAL__ | E73: =SUM(E70:E72) | F73: =SUM(F70:F72)
A74: 8 | B74: Investments | C74: Government securities | D74: BANK_INV_GS | E74: 0 | F74: 0
A75: 8 | B75: Investments | C75: Other approved securities | D75: BANK_INV_APPROVED | E75: 0 | F75: 0
A76: 8 | B76: Investments | C76: Shares | D76: BANK_INV_SH | E76: 0 | F76: 0
A77: 8 | B77: Investments | C77: Debentures / bonds | D77: BANK_INV_DB | E77: 0 | F77: 0
A78: 8 | B78: Investments | C78: Subsidiaries / JVs | D78: BANK_INV_SUB | E78: 0 | F78: 0
A79: 8 | B79: Investments | C79: Other investments | D79: BANK_INV_OTHER | E79: 0 | F79: 0
A80: 8 | B80: Investments | C80: Total — Investments | D80: __TOTAL__ | E80: =SUM(E74:E79) | F80: =SUM(F74:F79)
A81: 9 | B81: Advances | C81: Bills purchased / discounted | D81: BANK_ADV_BILLS | E81: 0 | F81: 0
A82: 9 | B82: Advances | C82: Cash credits / overdrafts / demand loans | D82: BANK_ADV_CC | E82: 0 | F82: 0
A83: 9 | B83: Advances | C83: Term loans | D83: BANK_ADV_TERM | E83: 0 | F83: 0
A84: 9 | B84: Advances | C84: Provision / impairment | D84: BANK_ADV_PROV | E84: 0 | F84: 0
A85: 9 | B85: Advances | C85: Total — Advances | D85: __TOTAL__ | E85: =SUM(E81:E84) | F85: =SUM(F81:F84)
A86: 10 | B86: Fixed Assets | C86: Premises | D86: BANK_FA_PREM | E86: 0 | F86: 0
A87: 10 | B87: Fixed Assets | C87: Other fixed assets | D87: BANK_FA_OTHER | E87: 0 | F87: 0
A88: 10 | B88: Fixed Assets | C88: CWIP | D88: BANK_FA_CWIP | E88: 0 | F88: 0
A89: 10 | B89: Fixed Assets | C89: Total — Fixed Assets | D89: __TOTAL__ | E89: =SUM(E86:E88) | F89: =SUM(F86:F88)
A90: 11 | B90: Other Assets | C90: Inter-office adjustments | D90: BANK_OA_IO | E90: 0 | F90: 0
A91: 11 | B91: Other Assets | C91: Interest accrued | D91: BANK_OA_INT | E91: 0 | F91: 0
A92: 11 | B92: Other Assets | C92: Tax paid in advance | D92: BANK_OA_TAX | E92: 0 | F92: 0
A93: 11 | B93: Other Assets | C93: Stationery / stamps | D93: BANK_OA_STAT | E93: 0 | F93: 0
A94: 11 | B94: Other Assets | C94: Non-banking assets | D94: BANK_OA_NBA | E94: 0 | F94: 0
A95: 11 | B95: Other Assets | C95: Other assets | D95: BANK_OA_OTHER | E95: 0 | F95: 0
A96: 11 | B96: Other Assets | C96: Total — Other Assets | D96: __TOTAL__ | E96: =SUM(E90:E95) | F96: =SUM(F90:F95)
A97: 12 | B97: Contingent Liabilities | C97: Claims not acknowledged as debts | D97: BANK_CL_CLAIMS | E97: 0 | F97: 0
A98: 12 | B98: Contingent Liabilities | C98: Partly paid investments | D98: BANK_CL_PART | E98: 0 | F98: 0
A99: 12 | B99: Contingent Liabilities | C99: Forward exchange contracts | D99: BANK_CL_FX | E99: 0 | F99: 0
A100: 12 | B100: Contingent Liabilities | C100: Guarantees | D100: BANK_CL_GUAR | E100: 0 | F100: 0
A101: 12 | B101: Contingent Liabilities | C101: Acceptances / endorsements | D101: BANK_CL_ACCEPT | E101: 0 | F101: 0
A102: 12 | B102: Contingent Liabilities | C102: Other contingent liabilities | D102: BANK_CL_OTHER | E102: 0 | F102: 0
A103: 12 | B103: Contingent Liabilities | C103: Total — Contingent Liabilities | D103: __TOTAL__ | E103: =SUM(E97:E102) | F103: =SUM(F97:F102)
A104: 13 | B104: Interest Earned | C104: Interest / discount on advances / bills | D104: BANK_IE_ADV | E104: 0 | F104: 0
...

Sheet COOPBANK
A1: Co-operative Bank
A2: Authority: RBI / Banking Regulation Act as adapted | Official source: https://www.rbi.org.in/
A3: =IF('AAH Basic Info'!B5="","","Address: "&'AAH Basic Info'!B5) | B3: =IF('AAH Basic Info'!B6="","","PAN: "&'AAH Basic Info'!B6) | C3: =IF('AAH Basic Info'!B7="","","GSTIN: "&'AAH Basic Info'!B7) | D3: =IF('AAH Basic Info'!B27="","",'AAH Basic Info'!B27)
A4: Entity Name | B4: Current Period | C4: Previous Period | D4: Presentation Unit | E4: Standalone / Consolidated
A5: =IF('AAH Basic Info'!B3="","",'AAH Basic Info'!B3) | B5: =IF('AAH Basic Info'!B9="","",'AAH Basic Info'!B9) | C5: =IF('AAH Basic Info'!B10="","",'AAH Basic Info'!B10) | D5: =IF('AAH Basic Info'!B24="","",'AAH Basic Info'!B24) | E5: =IF('AAH Basic Info'!B25="","",'AAH Basic Info'!B25)
A6: Form A — Balance Sheet
A7: Particulars | B7: Schedule | C7: Current Reporting Period | D7: Previous Reporting Period
A8: CAPITAL AND LIABILITIES
A9: Capital | B9: 1 | C9: =E47 | D9: =F47
A10: Reserves and Surplus | B10: 2 | C10: =E53 | D10: =F53
A11: Deposits | B11: 3 | C11: =E57 | D11: =F57
A12: Borrowings | B12: 4 | C12: =E60 | D12: =F60
A13: Other Liabilities and Provisions | B13: 5 | C13: =E66 | D13: =F66
A14: TOTAL CAPITAL AND LIABILITIES | C14: =SUM(C9,C10,C11,C12,C13) | D14: =SUM(D9,D10,D11,D12,D13)
A15: ASSETS
A16: Cash and Balances with Reserve Bank of India | B16: 6 | C16: =E69 | D16: =F69
A17: Balances with Banks and Money at Call and Short Notice | B17: 7 | C17: =E73 | D17: =F73
A18: Investments | B18: 8 | C18: =E80 | D18: =F80
A19: Advances | B19: 9 | C19: =E85 | D19: =F85
A20: Fixed Assets | B20: 10 | C20: =E89 | D20: =F89
A21: Other Assets | B21: 11 | C21: =E96 | D21: =F96
A22: TOTAL ASSETS | C22: =SUM(C16,C17,C18,C19,C20,C21) | D22: =SUM(D16,D17,D18,D19,D20,D21)
A23: CONTINGENT LIABILITIES
A24: Contingent Liabilities | B24: 12 | C24: =E103 | D24: =F103
A27: Form B — Profit and Loss Account
A28: Particulars | B28: Schedule | C28: Current Reporting Period | D28: Previous Reporting Period
A29: INCOME
A30: Interest Earned | B30: 13 | C30: =E108 | D30: =F108
A31: Other Income | B31: 14 | C31: =E114 | D31: =F114
A32: TOTAL INCOME | C32: =SUM(C30,C31) | D32: =SUM(D30,D31)
A33: EXPENDITURE
A34: Interest Expended | B34: 15 | C34: =E118 | D34: =F118
A35: Operating Expenses | B35: 16 | C35: =E131 | D35: =F131
A36: Provisions and Contingencies | B36: —
A37: TOTAL EXPENDITURE | C37: =SUM(C34,C35) | D37: =SUM(D34,D35)
A38: Profit / (Loss) before Tax | C38: =C32-C37 | D38: =D32-D37
A39: Tax | B39: —
A40: Net Profit / (Loss) | C40: =C38-SUM(C39) | D40: =D38-SUM(D39)
A43: Notes / Schedules — linked source for face statements
A44: Note | B44: Note Title | C44: Statutory Line Item | D44: AAH Mapping Key | E44: Current Period | F44: Previous Period | G44: Disclosure / Remarks
A45: 1 | B45: Capital | C45: Authorised capital | D45: BANK_CAP_AUTH | E45: 0 | F45: 0
A46: 1 | B46: Capital | C46: Issued / subscribed / paid-up capital | D46: BANK_CAP_PAID | E46: 0 | F46: 0
A47: 1 | B47: Capital | C47: Total — Capital | D47: __TOTAL__ | E47: =SUM(E45:E46) | F47: =SUM(F45:F46)
A48: 2 | B48: Reserves and Surplus | C48: Statutory reserve | D48: BANK_RES_STAT | E48: 0 | F48: 0
A49: 2 | B49: Reserves and Surplus | C49: Capital reserve | D49: BANK_RES_CAP | E49: 0 | F49: 0
A50: 2 | B50: Reserves and Surplus | C50: Share premium | D50: BANK_RES_SP | E50: 0 | F50: 0
A51: 2 | B51: Reserves and Surplus | C51: Revenue / other reserves | D51: BANK_RES_OTHER | E51: 0 | F51: 0
A52: 2 | B52: Reserves and Surplus | C52: Balance in P&L | D52: BANK_RES_PL | E52: 0 | F52: 0
A53: 2 | B53: Reserves and Surplus | C53: Total — Reserves and Surplus | D53: __TOTAL__ | E53: =SUM(E48:E52) | F53: =SUM(F48:F52)
A54: 3 | B54: Deposits | C54: Demand deposits | D54: BANK_DEP_DEM | E54: 0 | F54: 0
A55: 3 | B55: Deposits | C55: Savings bank deposits | D55: BANK_DEP_SAV | E55: 0 | F55: 0
A56: 3 | B56: Deposits | C56: Term deposits | D56: BANK_DEP_TERM | E56: 0 | F56: 0
A57: 3 | B57: Deposits | C57: Total — Deposits | D57: __TOTAL__ | E57: =SUM(E54:E56) | F57: =SUM(F54:F56)
A58: 4 | B58: Borrowings | C58: Borrowings in India | D58: BANK_BORR_IN | E58: 0 | F58: 0
A59: 4 | B59: Borrowings | C59: Borrowings outside India | D59: BANK_BORR_OUT | E59: 0 | F59: 0
A60: 4 | B60: Borrowings | C60: Total — Borrowings | D60: __TOTAL__ | E60: =SUM(E58:E59) | F60: =SUM(F58:F59)
A61: 5 | B61: Other Liabilities and Provisions | C61: Bills payable | D61: BANK_OL_BILLS | E61: 0 | F61: 0
A62: 5 | B62: Other Liabilities and Provisions | C62: Inter-office adjustments | D62: BANK_OL_IO | E62: 0 | F62: 0
A63: 5 | B63: Other Liabilities and Provisions | C63: Interest accrued | D63: BANK_OL_INT | E63: 0 | F63: 0
A64: 5 | B64: Other Liabilities and Provisions | C64: Other liabilities | D64: BANK_OL_OTHER | E64: 0 | F64: 0
A65: 5 | B65: Other Liabilities and Provisions | C65: Provisions | D65: BANK_OL_PROV | E65: 0 | F65: 0
A66: 5 | B66: Other Liabilities and Provisions | C66: Total — Other Liabilities and Provisions | D66: __TOTAL__ | E66: =SUM(E61:E65) | F66: =SUM(F61:F65)
A67: 6 | B67: Cash and Balances with RBI | C67: Cash in hand | D67: BANK_CASH | E67: 0 | F67: 0
A68: 6 | B68: Cash and Balances with RBI | C68: Balances with RBI | D68: BANK_RBI | E68: 0 | F68: 0
A69: 6 | B69: Cash and Balances with RBI | C69: Total — Cash and Balances with RBI | D69: __TOTAL__ | E69: =SUM(E67:E68) | F69: =SUM(F67:F68)
A70: 7 | B70: Balances with Banks and Money at Call / Short Notice | C70: Balances with banks in India | D70: BANK_BAL_IN | E70: 0 | F70: 0
A71: 7 | B71: Balances with Banks and Money at Call / Short Notice | C71: Money at call / short notice | D71: BANK_CALL | E71: 0 | F71: 0
A72: 7 | B72: Balances with Banks and Money at Call / Short Notice | C72: Balances outside India | D72: BANK_BAL_OUT | E72: 0 | F72: 0
A73: 7 | B73: Balances with Banks and Money at Call / Short Notice | C73: Total — Balances with Banks and Money at Call / Short Notice | D73: __TOTAL__ | E73: =SUM(E70:E72) | F73: =SUM(F70:F72)
A74: 8 | B74: Investments | C74: Government securities | D74: BANK_INV_GS | E74: 0 | F74: 0
A75: 8 | B75: Investments | C75: Other approved securities | D75: BANK_INV_APPROVED | E75: 0 | F75: 0
A76: 8 | B76: Investments | C76: Shares | D76: BANK_INV_SH | E76: 0 | F76: 0
A77: 8 | B77: Investments | C77: Debentures / bonds | D77: BANK_INV_DB | E77: 0 | F77: 0
A78: 8 | B78: Investments | C78: Subsidiaries / JVs | D78: BANK_INV_SUB | E78: 0 | F78: 0
A79: 8 | B79: Investments | C79: Other investments | D79: BANK_INV_OTHER | E79: 0 | F79: 0
A80: 8 | B80: Investments | C80: Total — Investments | D80: __TOTAL__ | E80: =SUM(E74:E79) | F80: =SUM(F74:F79)
A81: 9 | B81: Advances | C81: Bills purchased / discounted | D81: BANK_ADV_BILLS | E81: 0 | F81: 0
A82: 9 | B82: Advances | C82: Cash credits / overdrafts / demand loans | D82: BANK_ADV_CC | E82: 0 | F82: 0
A83: 9 | B83: Advances | C83: Term loans | D83: BANK_ADV_TERM | E83: 0 | F83: 0
A84: 9 | B84: Advances | C84: Provision / impairment | D84: BANK_ADV_PROV | E84: 0 | F84: 0
A85: 9 | B85: Advances | C85: Total — Advances | D85: __TOTAL__ | E85: =SUM(E81:E84) | F85: =SUM(F81:F84)
A86: 10 | B86: Fixed Assets | C86: Premises | D86: BANK_FA_PREM | E86: 0 | F86: 0
A87: 10 | B87: Fixed Assets | C87: Other fixed assets | D87: BANK_FA_OTHER | E87: 0 | F87: 0
A88: 10 | B88: Fixed Assets | C88: CWIP | D88: BANK_FA_CWIP | E88: 0 | F88: 0
A89: 10 | B89: Fixed Assets | C89: Total — Fixed Assets | D89: __TOTAL__ | E89: =SUM(E86:E88) | F89: =SUM(F86:F88)
A90: 11 | B90: Other Assets | C90: Inter-office adjustments | D90: BANK_OA_IO | E90: 0 | F90: 0
A91: 11 | B91: Other Assets | C91: Interest accrued | D91: BANK_OA_INT | E91: 0 | F91: 0
A92: 11 | B92: Other Assets | C92: Tax paid in advance | D92: BANK_OA_TAX | E92: 0 | F92: 0
A93: 11 | B93: Other Assets | C93: Stationery / stamps | D93: BANK_OA_STAT | E93: 0 | F93: 0
A94: 11 | B94: Other Assets | C94: Non-banking assets | D94: BANK_OA_NBA | E94: 0 | F94: 0
A95: 11 | B95: Other Assets | C95: Other assets | D95: BANK_OA_OTHER | E95: 0 | F95: 0
A96: 11 | B96: Other Assets | C96: Total — Other Assets | D96: __TOTAL__ | E96: =SUM(E90:E95) | F96: =SUM(F90:F95)
A97: 12 | B97: Contingent Liabilities | C97: Claims not acknowledged as debts | D97: BANK_CL_CLAIMS | E97: 0 | F97: 0
A98: 12 | B98: Contingent Liabilities | C98: Partly paid investments | D98: BANK_CL_PART | E98: 0 | F98: 0
A99: 12 | B99: Contingent Liabilities | C99: Forward exchange contracts | D99: BANK_CL_FX | E99: 0 | F99: 0
A100: 12 | B100: Contingent Liabilities | C100: Guarantees | D100: BANK_CL_GUAR | E100: 0 | F100: 0
A101: 12 | B101: Contingent Liabilities | C101: Acceptances / endorsements | D101: BANK_CL_ACCEPT | E101: 0 | F101: 0
A102: 12 | B102: Contingent Liabilities | C102: Other contingent liabilities | D102: BANK_CL_OTHER | E102: 0 | F102: 0
A103: 12 | B103: Contingent Liabilities | C103: Total — Contingent Liabilities | D103: __TOTAL__ | E103: =SUM(E97:E102) | F103: =SUM(F97:F102)
A104: 13 | B104: Interest Earned | C104: Interest / discount on advances / bills | D104: BANK_IE_ADV | E104: 0 | F104: 0
...

Sheet LIFE
A1: Life Insurance
A2: Authority: IRDAI | Official source: https://irdai.gov.in/
A3: =IF('AAH Basic Info'!B5="","","Address: "&'AAH Basic Info'!B5) | B3: =IF('AAH Basic Info'!B6="","","PAN: "&'AAH Basic Info'!B6) | C3: =IF('AAH Basic Info'!B7="","","GSTIN: "&'AAH Basic Info'!B7) | D3: =IF('AAH Basic Info'!B27="","",'AAH Basic Info'!B27)
A4: Entity Name | B4: Current Period | C4: Previous Period | D4: Presentation Unit | E4: Standalone / Consolidated
A5: =IF('AAH Basic Info'!B3="","",'AAH Basic Info'!B3) | B5: =IF('AAH Basic Info'!B9="","",'AAH Basic Info'!B9) | C5: =IF('AAH Basic Info'!B10="","",'AAH Basic Info'!B10) | D5: =IF('AAH Basic Info'!B24="","",'AAH Basic Info'!B24) | E5: =IF('AAH Basic Info'!B25="","",'AAH Basic Info'!B25)
A6: Form A-BS — Life Insurance Balance Sheet
A7: Particulars | B7: Schedule | C7: Current Reporting Period | D7: Previous Reporting Period
A8: SOURCES OF FUNDS
A9: Share Capital | B9: 1 | C9: =E51 | D9: =F51
A10: Reserves and Surplus | B10: 2 | C10: =E56 | D10: =F56
A11: Borrowings | B11: 3 | C11: =E58 | D11: =F58
A12: Policy Liabilities / Mathematical Reserves | B12: 12 | C12: =E77 | D12: =F77
A13: TOTAL SOURCES OF FUNDS | C13: =SUM(C9,C10,C11,C12) | D13: =SUM(D9,D10,D11,D12)
A14: APPLICATION OF FUNDS
A15: Investments - Shareholders | B15: 4 | C15: =E60 | D15: =F60
A16: Investments - Policyholders | B16: 5 | C16: =E62 | D16: =F62
A17: Loans | B17: 6 | C17: =E64 | D17: =F64
A18: Fixed Assets | B18: 7 | C18: =E66 | D18: =F66
A19: Cash and Bank Balances | B19: 8 | C19: =E68 | D19: =F68
A20: Advances and Other Assets | B20: 9 | C20: =E71 | D20: =F71
A21: Current Liabilities | B21: 10 | C21: =E73 | D21: =F73
A22: Provisions | B22: 11 | C22: =E75 | D22: =F75
A23: Fair Value Change Account | B23: 13 | C23: =E79 | D23: =F79
A24: Other / Miscellaneous Assets | B24: 14 | C24: =E81 | D24: =F81
A25: TOTAL APPLICATION OF FUNDS | C25: =SUM(C15,C16,C17,C18,C19,C20,C21,C22,C23,C24) | D25: =SUM(D15,D16,D17,D18,D19,D20,D21,D22,D23,D24)
A28: Policyholders' Revenue Account / Shareholders' Profit and Loss Account
A29: Particulars | B29: Schedule | C29: Current Reporting Period | D29: Previous Reporting Period
A30: POLICYHOLDERS' REVENUE ACCOUNT
A31: Premium Earned / Net | B31: 15 | C31: =E83 | D31: =F83
A32: Income from Investments | B32: 16 | C32: =E85 | D32: =F85
A33: Other Income | B33: —
A34: Commission | B34: 17 | C34: =E87 | D34: =F87
A35: Operating Expenses | B35: 18 | C35: =E89 | D35: =F89
A36: Benefits Paid | B36: 19 | C36: =E91 | D36: =F91
A37: Change in Valuation of Liability | B37: 20 | C37: =E93 | D37: =F93
A38: Surplus / (Deficit) | C38: =0 | D38: =0
A39: SHAREHOLDERS' PROFIT AND LOSS ACCOUNT
A40: Transfer from Policyholders' Account | B40: —
A41: Investment Income - Shareholders | B41: 16 | C41: =E85 | D41: =F85
A42: Other Income | B42: —
A43: Expenses / Provisions | B43: —
A44: Tax | B44: —
A45: Profit / (Loss) | C45: =C38-SUM(C40,C41,C42,C43,C44) | D45: =D38-SUM(D40,D41,D42,D43,D44)
A48: Notes / Schedules — linked source for face statements
A49: Note | B49: Note Title | C49: Statutory Line Item | D49: AAH Mapping Key | E49: Current Period | F49: Previous Period | G49: Disclosure / Remarks
A50: 1 | B50: Share Capital | C50: Share capital | D50: INS_CAP | E50: 0 | F50: 0
A51: 1 | B51: Share Capital | C51: Total — Share Capital | D51: __TOTAL__ | E51: =SUM(E50:E50) | F51: =SUM(F50:F50)
A52: 2 | B52: Reserves and Surplus | C52: Capital reserve | D52: INS_RES_CAP | E52: 0 | F52: 0
A53: 2 | B53: Reserves and Surplus | C53: Share premium | D53: INS_RES_SP | E53: 0 | F53: 0
A54: 2 | B54: Reserves and Surplus | C54: Other reserves | D54: INS_RES_OTHER | E54: 0 | F54: 0
A55: 2 | B55: Reserves and Surplus | C55: P&L balance | D55: INS_RES_PL | E55: 0 | F55: 0
A56: 2 | B56: Reserves and Surplus | C56: Total — Reserves and Surplus | D56: __TOTAL__ | E56: =SUM(E52:E55) | F56: =SUM(F52:F55)
A57: 3 | B57: Borrowings | C57: Borrowings | D57: INS_BORR | E57: 0 | F57: 0
A58: 3 | B58: Borrowings | C58: Total — Borrowings | D58: __TOTAL__ | E58: =SUM(E57:E57) | F58: =SUM(F57:F57)
A59: 4 | B59: Investments - Shareholders | C59: Shareholders' investments | D59: INS_INV_SH | E59: 0 | F59: 0
A60: 4 | B60: Investments - Shareholders | C60: Total — Investments - Shareholders | D60: __TOTAL__ | E60: =SUM(E59:E59) | F60: =SUM(F59:F59)
A61: 5 | B61: Investments - Policyholders | C61: Policyholders' investments | D61: INS_INV_PH | E61: 0 | F61: 0
A62: 5 | B62: Investments - Policyholders | C62: Total — Investments - Policyholders | D62: __TOTAL__ | E62: =SUM(E61:E61) | F62: =SUM(F61:F61)
A63: 6 | B63: Loans | C63: Loans | D63: INS_LOANS | E63: 0 | F63: 0
A64: 6 | B64: Loans | C64: Total — Loans | D64: __TOTAL__ | E64: =SUM(E63:E63) | F64: =SUM(F63:F63)
A65: 7 | B65: Fixed Assets | C65: Fixed assets | D65: INS_FA | E65: 0 | F65: 0
A66: 7 | B66: Fixed Assets | C66: Total — Fixed Assets | D66: __TOTAL__ | E66: =SUM(E65:E65) | F66: =SUM(F65:F65)
A67: 8 | B67: Cash and Bank Balances | C67: Cash and bank balances | D67: INS_CASH | E67: 0 | F67: 0
A68: 8 | B68: Cash and Bank Balances | C68: Total — Cash and Bank Balances | D68: __TOTAL__ | E68: =SUM(E67:E67) | F68: =SUM(F67:F67)
A69: 9 | B69: Advances and Other Assets | C69: Advances | D69: INS_ADV | E69: 0 | F69: 0
A70: 9 | B70: Advances and Other Assets | C70: Other assets | D70: INS_OA | E70: 0 | F70: 0
A71: 9 | B71: Advances and Other Assets | C71: Total — Advances and Other Assets | D71: __TOTAL__ | E71: =SUM(E69:E70) | F71: =SUM(F69:F70)
A72: 10 | B72: Current Liabilities | C72: Current liabilities | D72: INS_CL | E72: 0 | F72: 0
A73: 10 | B73: Current Liabilities | C73: Total — Current Liabilities | D73: __TOTAL__ | E73: =SUM(E72:E72) | F73: =SUM(F72:F72)
A74: 11 | B74: Provisions | C74: Provisions | D74: INS_PROV | E74: 0 | F74: 0
A75: 11 | B75: Provisions | C75: Total — Provisions | D75: __TOTAL__ | E75: =SUM(E74:E74) | F75: =SUM(F74:F74)
A76: 12 | B76: Policy Liabilities / Mathematical Reserves | C76: Policy liabilities / mathematical reserves | D76: INS_POLLIAB | E76: 0 | F76: 0
A77: 12 | B77: Policy Liabilities / Mathematical Reserves | C77: Total — Policy Liabilities / Mathematical Reserves | D77: __TOTAL__ | E77: =SUM(E76:E76) | F77: =SUM(F76:F76)
A78: 13 | B78: Fair Value Change Account | C78: Fair value change account | D78: INS_FVCA | E78: 0 | F78: 0
A79: 13 | B79: Fair Value Change Account | C79: Total — Fair Value Change Account | D79: __TOTAL__ | E79: =SUM(E78:E78) | F79: =SUM(F78:F78)
A80: 14 | B80: Other / Miscellaneous Assets | C80: Other / miscellaneous assets | D80: INS_MISC | E80: 0 | F80: 0
A81: 14 | B81: Other / Miscellaneous Assets | C81: Total — Other / Miscellaneous Assets | D81: __TOTAL__ | E81: =SUM(E80:E80) | F81: =SUM(F80:F80)
A82: 15 | B82: Premium Earned / Net | C82: Premium | D82: INS_PREM | E82: 0 | F82: 0
A83: 15 | B83: Premium Earned / Net | C83: Total — Premium Earned / Net | D83: __TOTAL__ | E83: =SUM(E82:E82) | F83: =SUM(F82:F82)
A84: 16 | B84: Income from Investments | C84: Investment income | D84: INS_INVINC | E84: 0 | F84: 0
A85: 16 | B85: Income from Investments | C85: Total — Income from Investments | D85: __TOTAL__ | E85: =SUM(E84:E84) | F85: =SUM(F84:F84)
A86: 17 | B86: Commission | C86: Commission | D86: INS_COMM | E86: 0 | F86: 0
A87: 17 | B87: Commission | C87: Total — Commission | D87: __TOTAL__ | E87: =SUM(E86:E86) | F87: =SUM(F86:F86)
A88: 18 | B88: Operating Expenses | C88: Operating expenses | D88: INS_OPEX | E88: 0 | F88: 0
A89: 18 | B89: Operating Expenses | C89: Total — Operating Expenses | D89: __TOTAL__ | E89: =SUM(E88:E88) | F89: =SUM(F88:F88)
A90: 19 | B90: Benefits Paid | C90: Benefits paid | D90: INS_BEN | E90: 0 | F90: 0
A91: 19 | B91: Benefits Paid | C91: Total — Benefits Paid | D91: __TOTAL__ | E91: =SUM(E90:E90) | F91: =SUM(F90:F90)
A92: 20 | B92: Change in Valuation of Liability | C92: Change in valuation of liability | D92: INS_CHGVAL | E92: 0 | F92: 0
A93: 20 | B93: Change in Valuation of Liability | C93: Total — Change in Valuation of Liability | D93: __TOTAL__ | E93: =SUM(E92:E92) | F93: =SUM(F92:F92)
A96: Validation
A97: Check | B97: Current Period | C97: Previous Period | D97: Result
A98: Balance Sheet difference
A99: Notes / disclosures | B99: Review | C99: Review | D99: Review
A100: Profile readiness | D100: READY FOR REVIEW
A104: Signatures / Certification
A105: Entity Signatory | B105: ='AAH Basic Info'!B13 | C105: Designation | D105: ='AAH Basic Info'!B14 | E105: DIN | F105: ='AAH Basic Info'!B15
A106: Signing Date | B106: ='AAH Basic Info'!B16 | C106: Place | D106: ='AAH Basic Info'!B17
A107: Audit Firm | B107: ='AAH Basic Info'!B18 | C107: FRN | D107: ='AAH Basic Info'!B19
A108: Signing CA | B108: ='AAH Basic Info'!B20 | C108: Designation | D108: ='AAH Basic Info'!B21 | E108: Membership No. | F108: ='AAH Basic Info'!B22
A109: Audit Place | B109: ='AAH Basic Info'!B23 | C109: Signing Date | D109: ='AAH Basic Info'!B30

Sheet GENINS
A1: General Insurance
A2: Authority: IRDAI | Official source: https://irdai.gov.in/
A3: =IF('AAH Basic Info'!B5="","","Address: "&'AAH Basic Info'!B5) | B3: =IF('AAH Basic Info'!B6="","","PAN: "&'AAH Basic Info'!B6) | C3: =IF('AAH Basic Info'!B7="","","GSTIN: "&'AAH Basic Info'!B7) | D3: =IF('AAH Basic Info'!B27="","",'AAH Basic Info'!B27)
A4: Entity Name | B4: Current Period | C4: Previous Period | D4: Presentation Unit | E4: Standalone / Consolidated
A5: =IF('AAH Basic Info'!B3="","",'AAH Basic Info'!B3) | B5: =IF('AAH Basic Info'!B9="","",'AAH Basic Info'!B9) | C5: =IF('AAH Basic Info'!B10="","",'AAH Basic Info'!B10) | D5: =IF('AAH Basic Info'!B24="","",'AAH Basic Info'!B24) | E5: =IF('AAH Basic Info'!B25="","",'AAH Basic Info'!B25)
A6: Form B-BS — Balance Sheet
A7: Particulars | B7: Schedule | C7: Current Reporting Period | D7: Previous Reporting Period
A8: SOURCES OF FUNDS
A9: Share Capital | B9: 1 | C9: =E48 | D9: =F48
A10: Reserves and Surplus | B10: 2 | C10: =E50 | D10: =F50
A11: Borrowings | B11: 3 | C11: =E52 | D11: =F52
A12: TOTAL SOURCES OF FUNDS | C12: =SUM(C9,C10,C11) | D12: =SUM(D9,D10,D11)
A13: APPLICATION OF FUNDS
A14: Investments | B14: 4 | C14: =E54 | D14: =F54
A15: Loans | B15: 5 | C15: =E56 | D15: =F56
A16: Fixed Assets | B16: 6 | C16: =E58 | D16: =F58
A17: Cash and Bank Balances | B17: 7 | C17: =E60 | D17: =F60
A18: Advances and Other Assets | B18: 8 | C18: =E62 | D18: =F62
A19: Current Liabilities | B19: 9 | C19: =E64 | D19: =F64
A20: Provisions | B20: 10 | C20: =E66 | D20: =F66
A21: Fair Value Change Account | B21: 11 | C21: =E68 | D21: =F68
A22: Insurance / Regulatory Reserves | B22: 18 | C22: =E82 | D22: =F82
A23: TOTAL APPLICATION OF FUNDS | C23: =SUM(C14,C15,C16,C17,C18,C19,C20,C21,C22) | D23: =SUM(D14,D15,D16,D17,D18,D19,D20,D21,D22)
A26: Revenue Account / Profit and Loss Account
A27: Particulars | B27: Schedule | C27: Current Reporting Period | D27: Previous Reporting Period
A28: REVENUE ACCOUNT
A29: Premium Earned (Net) | B29: 12 | C29: =E70 | D29: =F70
A30: Claims Incurred (Net) | B30: 13 | C30: =E72 | D30: =F72
A31: Commission | B31: 14 | C31: =E74 | D31: =F74
A32: Operating Expenses | B32: 15 | C32: =E76 | D32: =F76
A33: Investment Income | B33: 16 | C33: =E78 | D33: =F78
A34: Other Income | B34: 17 | C34: =E80 | D34: =F80
A35: Operating Profit / (Loss) | C35: =0 | D35: =0
A36: PROFIT AND LOSS ACCOUNT
A37: Transfer from Revenue Accounts | B37: —
A38: Investment Income | B38: 16 | C38: =E78 | D38: =F78
A39: Other Income | B39: 17 | C39: =E80 | D39: =F80
A40: Other Expenses / Provisions | B40: —
A41: Tax | B41: —
A42: Profit / (Loss) | C42: =C35-SUM(C37,C38,C39,C40,C41) | D42: =D35-SUM(D37,D38,D39,D40,D41)
A45: Notes / Schedules — linked source for face statements
A46: Note | B46: Note Title | C46: Statutory Line Item | D46: AAH Mapping Key | E46: Current Period | F46: Previous Period | G46: Disclosure / Remarks
A47: 1 | B47: Share Capital | C47: Share capital | D47: GEN_CAP | E47: 0 | F47: 0
A48: 1 | B48: Share Capital | C48: Total — Share Capital | D48: __TOTAL__ | E48: =SUM(E47:E47) | F48: =SUM(F47:F47)
A49: 2 | B49: Reserves and Surplus | C49: Reserves and surplus | D49: GEN_RES | E49: 0 | F49: 0
A50: 2 | B50: Reserves and Surplus | C50: Total — Reserves and Surplus | D50: __TOTAL__ | E50: =SUM(E49:E49) | F50: =SUM(F49:F49)
A51: 3 | B51: Borrowings | C51: Borrowings | D51: GEN_BORR | E51: 0 | F51: 0
A52: 3 | B52: Borrowings | C52: Total — Borrowings | D52: __TOTAL__ | E52: =SUM(E51:E51) | F52: =SUM(F51:F51)
A53: 4 | B53: Investments | C53: Investments | D53: GEN_INV | E53: 0 | F53: 0
A54: 4 | B54: Investments | C54: Total — Investments | D54: __TOTAL__ | E54: =SUM(E53:E53) | F54: =SUM(F53:F53)
A55: 5 | B55: Loans | C55: Loans | D55: GEN_LOANS | E55: 0 | F55: 0
A56: 5 | B56: Loans | C56: Total — Loans | D56: __TOTAL__ | E56: =SUM(E55:E55) | F56: =SUM(F55:F55)
A57: 6 | B57: Fixed Assets | C57: Fixed assets | D57: GEN_FA | E57: 0 | F57: 0
A58: 6 | B58: Fixed Assets | C58: Total — Fixed Assets | D58: __TOTAL__ | E58: =SUM(E57:E57) | F58: =SUM(F57:F57)
A59: 7 | B59: Cash and Bank Balances | C59: Cash and bank balances | D59: GEN_CASH | E59: 0 | F59: 0
A60: 7 | B60: Cash and Bank Balances | C60: Total — Cash and Bank Balances | D60: __TOTAL__ | E60: =SUM(E59:E59) | F60: =SUM(F59:F59)
A61: 8 | B61: Advances and Other Assets | C61: Advances and other assets | D61: GEN_ADV | E61: 0 | F61: 0
A62: 8 | B62: Advances and Other Assets | C62: Total — Advances and Other Assets | D62: __TOTAL__ | E62: =SUM(E61:E61) | F62: =SUM(F61:F61)
A63: 9 | B63: Current Liabilities | C63: Current liabilities | D63: GEN_CL | E63: 0 | F63: 0
A64: 9 | B64: Current Liabilities | C64: Total — Current Liabilities | D64: __TOTAL__ | E64: =SUM(E63:E63) | F64: =SUM(F63:F63)
A65: 10 | B65: Provisions | C65: Provisions | D65: GEN_PROV | E65: 0 | F65: 0
A66: 10 | B66: Provisions | C66: Total — Provisions | D66: __TOTAL__ | E66: =SUM(E65:E65) | F66: =SUM(F65:F65)
A67: 11 | B67: Fair Value Change Account | C67: Fair value change account | D67: GEN_FV | E67: 0 | F67: 0
A68: 11 | B68: Fair Value Change Account | C68: Total — Fair Value Change Account | D68: __TOTAL__ | E68: =SUM(E67:E67) | F68: =SUM(F67:F67)
A69: 12 | B69: Premium Earned (Net) | C69: Premium earned | D69: GEN_PREM | E69: 0 | F69: 0
A70: 12 | B70: Premium Earned (Net) | C70: Total — Premium Earned (Net) | D70: __TOTAL__ | E70: =SUM(E69:E69) | F70: =SUM(F69:F69)
A71: 13 | B71: Claims Incurred (Net) | C71: Claims incurred | D71: GEN_CLAIMS | E71: 0 | F71: 0
A72: 13 | B72: Claims Incurred (Net) | C72: Total — Claims Incurred (Net) | D72: __TOTAL__ | E72: =SUM(E71:E71) | F72: =SUM(F71:F71)
A73: 14 | B73: Commission | C73: Commission | D73: GEN_COMM | E73: 0 | F73: 0
A74: 14 | B74: Commission | C74: Total — Commission | D74: __TOTAL__ | E74: =SUM(E73:E73) | F74: =SUM(F73:F73)
A75: 15 | B75: Operating Expenses | C75: Operating expenses | D75: GEN_OPEX | E75: 0 | F75: 0
A76: 15 | B76: Operating Expenses | C76: Total — Operating Expenses | D76: __TOTAL__ | E76: =SUM(E75:E75) | F76: =SUM(F75:F75)
A77: 16 | B77: Investment Income | C77: Investment income | D77: GEN_INVINC | E77: 0 | F77: 0
A78: 16 | B78: Investment Income | C78: Total — Investment Income | D78: __TOTAL__ | E78: =SUM(E77:E77) | F78: =SUM(F77:F77)
A79: 17 | B79: Other Income | C79: Other income | D79: GEN_OI | E79: 0 | F79: 0
A80: 17 | B80: Other Income | C80: Total — Other Income | D80: __TOTAL__ | E80: =SUM(E79:E79) | F80: =SUM(F79:F79)
A81: 18 | B81: Insurance / Regulatory Reserves | C81: Insurance / regulatory reserves | D81: GEN_REGRES | E81: 0 | F81: 0
A82: 18 | B82: Insurance / Regulatory Reserves | C82: Total — Insurance / Regulatory Reserves | D82: __TOTAL__ | E82: =SUM(E81:E81) | F82: =SUM(F81:F81)
A85: Validation
A86: Check | B86: Current Period | C86: Previous Period | D86: Result
A87: Balance Sheet difference
A88: Notes / disclosures | B88: Review | C88: Review | D88: Review
A89: Profile readiness | D89: READY FOR REVIEW
A93: Signatures / Certification
A94: Entity Signatory | B94: ='AAH Basic Info'!B13 | C94: Designation | D94: ='AAH Basic Info'!B14 | E94: DIN | F94: ='AAH Basic Info'!B15
A95: Signing Date | B95: ='AAH Basic Info'!B16 | C95: Place | D95: ='AAH Basic Info'!B17
A96: Audit Firm | B96: ='AAH Basic Info'!B18 | C96: FRN | D96: ='AAH Basic Info'!B19
A97: Signing CA | B97: ='AAH Basic Info'!B20 | C97: Designation | D97: ='AAH Basic Info'!B21 | E97: Membership No. | F97: ='AAH Basic Info'!B22
A98: Audit Place | B98: ='AAH Basic Info'!B23 | C98: Signing Date | D98: ='AAH Basic Info'!B30

Sheet REINS
A1: Reinsurance
A2: Authority: IRDAI | Official source: https://irdai.gov.in/
A3: =IF('AAH Basic Info'!B5="","","Address: "&'AAH Basic Info'!B5) | B3: =IF('AAH Basic Info'!B6="","","PAN: "&'AAH Basic Info'!B6) | C3: =IF('AAH Basic Info'!B7="","","GSTIN: "&'AAH Basic Info'!B7) | D3: =IF('AAH Basic Info'!B27="","",'AAH Basic Info'!B27)
A4: Entity Name | B4: Current Period | C4: Previous Period | D4: Presentation Unit | E4: Standalone / Consolidated
A5: =IF('AAH Basic Info'!B3="","",'AAH Basic Info'!B3) | B5: =IF('AAH Basic Info'!B9="","",'AAH Basic Info'!B9) | C5: =IF('AAH Basic Info'!B10="","",'AAH Basic Info'!B10) | D5: =IF('AAH Basic Info'!B24="","",'AAH Basic Info'!B24) | E5: =IF('AAH Basic Info'!B25="","",'AAH Basic Info'!B25)
A6: Form B-BS — Balance Sheet
A7: Particulars | B7: Schedule | C7: Current Reporting Period | D7: Previous Reporting Period
A8: SOURCES OF FUNDS
A9: Share Capital | B9: 1 | C9: =E48 | D9: =F48
A10: Reserves and Surplus | B10: 2 | C10: =E50 | D10: =F50
A11: Borrowings | B11: 3 | C11: =E52 | D11: =F52
A12: TOTAL SOURCES OF FUNDS | C12: =SUM(C9,C10,C11) | D12: =SUM(D9,D10,D11)
A13: APPLICATION OF FUNDS
A14: Investments | B14: 4 | C14: =E54 | D14: =F54
A15: Loans | B15: 5 | C15: =E56 | D15: =F56
A16: Fixed Assets | B16: 6 | C16: =E58 | D16: =F58
A17: Cash and Bank Balances | B17: 7 | C17: =E60 | D17: =F60
A18: Advances and Other Assets | B18: 8 | C18: =E62 | D18: =F62
A19: Current Liabilities | B19: 9 | C19: =E64 | D19: =F64
A20: Provisions | B20: 10 | C20: =E66 | D20: =F66
A21: Fair Value Change Account | B21: 11 | C21: =E68 | D21: =F68
A22: Insurance / Regulatory Reserves | B22: 18 | C22: =E82 | D22: =F82
A23: TOTAL APPLICATION OF FUNDS | C23: =SUM(C14,C15,C16,C17,C18,C19,C20,C21,C22) | D23: =SUM(D14,D15,D16,D17,D18,D19,D20,D21,D22)
A26: Revenue Account / Profit and Loss Account
A27: Particulars | B27: Schedule | C27: Current Reporting Period | D27: Previous Reporting Period
A28: REVENUE ACCOUNT
A29: Premium Earned (Net) | B29: 12 | C29: =E70 | D29: =F70
A30: Claims Incurred (Net) | B30: 13 | C30: =E72 | D30: =F72
A31: Commission | B31: 14 | C31: =E74 | D31: =F74
A32: Operating Expenses | B32: 15 | C32: =E76 | D32: =F76
A33: Investment Income | B33: 16 | C33: =E78 | D33: =F78
A34: Other Income | B34: 17 | C34: =E80 | D34: =F80
A35: Operating Profit / (Loss) | C35: =0 | D35: =0
A36: PROFIT AND LOSS ACCOUNT
A37: Transfer from Revenue Accounts | B37: —
A38: Investment Income | B38: 16 | C38: =E78 | D38: =F78
A39: Other Income | B39: 17 | C39: =E80 | D39: =F80
A40: Other Expenses / Provisions | B40: —
A41: Tax | B41: —
A42: Profit / (Loss) | C42: =C35-SUM(C37,C38,C39,C40,C41) | D42: =D35-SUM(D37,D38,D39,D40,D41)
A45: Notes / Schedules — linked source for face statements
A46: Note | B46: Note Title | C46: Statutory Line Item | D46: AAH Mapping Key | E46: Current Period | F46: Previous Period | G46: Disclosure / Remarks
A47: 1 | B47: Share Capital | C47: Share capital | D47: GEN_CAP | E47: 0 | F47: 0
A48: 1 | B48: Share Capital | C48: Total — Share Capital | D48: __TOTAL__ | E48: =SUM(E47:E47) | F48: =SUM(F47:F47)
A49: 2 | B49: Reserves and Surplus | C49: Reserves and surplus | D49: GEN_RES | E49: 0 | F49: 0
A50: 2 | B50: Reserves and Surplus | C50: Total — Reserves and Surplus | D50: __TOTAL__ | E50: =SUM(E49:E49) | F50: =SUM(F49:F49)
A51: 3 | B51: Borrowings | C51: Borrowings | D51: GEN_BORR | E51: 0 | F51: 0
A52: 3 | B52: Borrowings | C52: Total — Borrowings | D52: __TOTAL__ | E52: =SUM(E51:E51) | F52: =SUM(F51:F51)
A53: 4 | B53: Investments | C53: Investments | D53: GEN_INV | E53: 0 | F53: 0
A54: 4 | B54: Investments | C54: Total — Investments | D54: __TOTAL__ | E54: =SUM(E53:E53) | F54: =SUM(F53:F53)
A55: 5 | B55: Loans | C55: Loans | D55: GEN_LOANS | E55: 0 | F55: 0
A56: 5 | B56: Loans | C56: Total — Loans | D56: __TOTAL__ | E56: =SUM(E55:E55) | F56: =SUM(F55:F55)
A57: 6 | B57: Fixed Assets | C57: Fixed assets | D57: GEN_FA | E57: 0 | F57: 0
A58: 6 | B58: Fixed Assets | C58: Total — Fixed Assets | D58: __TOTAL__ | E58: =SUM(E57:E57) | F58: =SUM(F57:F57)
A59: 7 | B59: Cash and Bank Balances | C59: Cash and bank balances | D59: GEN_CASH | E59: 0 | F59: 0
A60: 7 | B60: Cash and Bank Balances | C60: Total — Cash and Bank Balances | D60: __TOTAL__ | E60: =SUM(E59:E59) | F60: =SUM(F59:F59)
A61: 8 | B61: Advances and Other Assets | C61: Advances and other assets | D61: GEN_ADV | E61: 0 | F61: 0
A62: 8 | B62: Advances and Other Assets | C62: Total — Advances and Other Assets | D62: __TOTAL__ | E62: =SUM(E61:E61) | F62: =SUM(F61:F61)
A63: 9 | B63: Current Liabilities | C63: Current liabilities | D63: GEN_CL | E63: 0 | F63: 0
A64: 9 | B64: Current Liabilities | C64: Total — Current Liabilities | D64: __TOTAL__ | E64: =SUM(E63:E63) | F64: =SUM(F63:F63)
A65: 10 | B65: Provisions | C65: Provisions | D65: GEN_PROV | E65: 0 | F65: 0
A66: 10 | B66: Provisions | C66: Total — Provisions | D66: __TOTAL__ | E66: =SUM(E65:E65) | F66: =SUM(F65:F65)
A67: 11 | B67: Fair Value Change Account | C67: Fair value change account | D67: GEN_FV | E67: 0 | F67: 0
A68: 11 | B68: Fair Value Change Account | C68: Total — Fair Value Change Account | D68: __TOTAL__ | E68: =SUM(E67:E67) | F68: =SUM(F67:F67)
A69: 12 | B69: Premium Earned (Net) | C69: Premium earned | D69: GEN_PREM | E69: 0 | F69: 0
A70: 12 | B70: Premium Earned (Net) | C70: Total — Premium Earned (Net) | D70: __TOTAL__ | E70: =SUM(E69:E69) | F70: =SUM(F69:F69)
A71: 13 | B71: Claims Incurred (Net) | C71: Claims incurred | D71: GEN_CLAIMS | E71: 0 | F71: 0
A72: 13 | B72: Claims Incurred (Net) | C72: Total — Claims Incurred (Net) | D72: __TOTAL__ | E72: =SUM(E71:E71) | F72: =SUM(F71:F71)
A73: 14 | B73: Commission | C73: Commission | D73: GEN_COMM | E73: 0 | F73: 0
A74: 14 | B74: Commission | C74: Total — Commission | D74: __TOTAL__ | E74: =SUM(E73:E73) | F74: =SUM(F73:F73)
A75: 15 | B75: Operating Expenses | C75: Operating expenses | D75: GEN_OPEX | E75: 0 | F75: 0
A76: 15 | B76: Operating Expenses | C76: Total — Operating Expenses | D76: __TOTAL__ | E76: =SUM(E75:E75) | F76: =SUM(F75:F75)
A77: 16 | B77: Investment Income | C77: Investment income | D77: GEN_INVINC | E77: 0 | F77: 0
A78: 16 | B78: Investment Income | C78: Total — Investment Income | D78: __TOTAL__ | E78: =SUM(E77:E77) | F78: =SUM(F77:F77)
A79: 17 | B79: Other Income | C79: Other income | D79: GEN_OI | E79: 0 | F79: 0
A80: 17 | B80: Other Income | C80: Total — Other Income | D80: __TOTAL__ | E80: =SUM(E79:E79) | F80: =SUM(F79:F79)
A81: 18 | B81: Insurance / Regulatory Reserves | C81: Insurance / regulatory reserves | D81: GEN_REGRES | E81: 0 | F81: 0
A82: 18 | B82: Insurance / Regulatory Reserves | C82: Total — Insurance / Regulatory Reserves | D82: __TOTAL__ | E82: =SUM(E81:E81) | F82: =SUM(F81:F81)
A85: Validation
A86: Check | B86: Current Period | C86: Previous Period | D86: Result
A87: Balance Sheet difference
A88: Notes / disclosures | B88: Review | C88: Review | D88: Review
A89: Profile readiness | D89: READY FOR REVIEW
A93: Signatures / Certification
A94: Entity Signatory | B94: ='AAH Basic Info'!B13 | C94: Designation | D94: ='AAH Basic Info'!B14 | E94: DIN | F94: ='AAH Basic Info'!B15
A95: Signing Date | B95: ='AAH Basic Info'!B16 | C95: Place | D95: ='AAH Basic Info'!B17
A96: Audit Firm | B96: ='AAH Basic Info'!B18 | C96: FRN | D96: ='AAH Basic Info'!B19
A97: Signing CA | B97: ='AAH Basic Info'!B20 | C97: Designation | D97: ='AAH Basic Info'!B21 | E97: Membership No. | F97: ='AAH Basic Info'!B22
A98: Audit Place | B98: ='AAH Basic Info'!B23 | C98: Signing Date | D98: ='AAH Basic Info'!B30

Sheet MF
A1: Mutual Fund Scheme
A2: Authority: SEBI | Official source: https://www.sebi.gov.in/legal/regulations/jul-2026/securities-and-exchange-board-of-india-mutual-funds-regulations-2026-last-amended-on-july-7-2026-_102780.html
A3: =IF('AAH Basic Info'!B5="","","Address: "&'AAH Basic Info'!B5) | B3: =IF('AAH Basic Info'!B6="","","PAN: "&'AAH Basic Info'!B6) | C3: =IF('AAH Basic Info'!B7="","","GSTIN: "&'AAH Basic Info'!B7) | D3: =IF('AAH Basic Info'!B27="","",'AAH Basic Info'!B27)
A4: Entity Name | B4: Current Period | C4: Previous Period | D4: Presentation Unit | E4: Standalone / Consolidated
A5: =IF('AAH Basic Info'!B3="","",'AAH Basic Info'!B3) | B5: =IF('AAH Basic Info'!B9="","",'AAH Basic Info'!B9) | C5: =IF('AAH Basic Info'!B10="","",'AAH Basic Info'!B10) | D5: =IF('AAH Basic Info'!B24="","",'AAH Basic Info'!B24) | E5: =IF('AAH Basic Info'!B25="","",'AAH Basic Info'!B25)
A6: Scheme-wise Balance Sheet
A7: Particulars | B7: Note No. | C7: Current Reporting Period | D7: Previous Reporting Period
A8: LIABILITIES
A9: Unit Capital | B9: 1 | C9: =E41 | D9: =F41
A10: Reserves and Surplus | B10: 2 | C10: =E43 | D10: =F43
A11: Current Liabilities and Provisions | B11: 10 | C11: =E62 | D11: =F62
A12: TOTAL LIABILITIES | C12: =SUM(C9,C10,C11) | D12: =SUM(D9,D10,D11)
A13: ASSETS
A14: Investments - Equity Shares | B14: 3 | C14: =E45 | D14: =F45
A15: Investments - Preference Shares | B15: 4 | C15: =E47 | D15: =F47
A16: Investments - Debentures / Bonds | B16: 5 | C16: =E49 | D16: =F49
A17: Investments - Government Securities | B17: 6 | C17: =E51 | D17: =F51
A18: Investments - Money Market Instruments | B18: 7 | C18: =E53 | D18: =F53
A19: Other Investments | B19: 8 | C19: =E55 | D19: =F55
A20: Current Assets | B20: 9 | C20: =E59 | D20: =F59
A21: TOTAL ASSETS | C21: =SUM(C14,C15,C16,C17,C18,C19,C20) | D21: =SUM(D14,D15,D16,D17,D18,D19,D20)
A24: Scheme-wise Revenue Account
A25: Particulars | B25: Note No. | C25: Current Reporting Period | D25: Previous Reporting Period
A26: REVENUE ACCOUNT
A27: Investment Income | B27: 11 | C27: =E64 | D27: =F64
A28: Profit / Loss on Sale of Investments | B28: 12 | C28: =E66 | D28: =F66
A29: Unrealised Appreciation / Depreciation | B29: 13 | C29: =E68 | D29: =F68
A30: Management Fees | B30: 14 | C30: =E70 | D30: =F70
A31: Trustee / Custodian / Other Expenses | B31: 15 | C31: =E72 | D31: =F72
A32: Surplus / (Deficit) | C32: =0 | D32: =0
A35: Notes / Schedules — linked source for face statements
A36: Note | B36: Note Title | C36: Statutory Line Item | D36: AAH Mapping Key | E36: Current Period | F36: Previous Period | G36: Disclosure / Remarks
A37: 1 | B37: Unit Capital | C37: Opening unit capital | D37: MF_UNIT_OPEN | E37: 0 | F37: 0
A38: 1 | B38: Unit Capital | C38: Units issued | D38: MF_UNIT_ISS | E38: 0 | F38: 0
A39: 1 | B39: Unit Capital | C39: Units redeemed | D39: MF_UNIT_RED | E39: 0 | F39: 0
A40: 1 | B40: Unit Capital | C40: Closing unit capital | D40: MF_UNIT_CLOSE | E40: 0 | F40: 0
A41: 1 | B41: Unit Capital | C41: Total — Unit Capital | D41: __TOTAL__ | E41: =SUM(E37:E40) | F41: =SUM(F37:F40)
A42: 2 | B42: Reserves and Surplus | C42: Reserves and surplus | D42: MF_RES | E42: 0 | F42: 0
A43: 2 | B43: Reserves and Surplus | C43: Total — Reserves and Surplus | D43: __TOTAL__ | E43: =SUM(E42:E42) | F43: =SUM(F42:F42)
A44: 3 | B44: Investments - Equity Shares | C44: Equity shares | D44: MF_INV_EQ | E44: 0 | F44: 0
A45: 3 | B45: Investments - Equity Shares | C45: Total — Investments - Equity Shares | D45: __TOTAL__ | E45: =SUM(E44:E44) | F45: =SUM(F44:F44)
A46: 4 | B46: Investments - Preference Shares | C46: Preference shares | D46: MF_INV_PREF | E46: 0 | F46: 0
A47: 4 | B47: Investments - Preference Shares | C47: Total — Investments - Preference Shares | D47: __TOTAL__ | E47: =SUM(E46:E46) | F47: =SUM(F46:F46)
A48: 5 | B48: Investments - Debentures / Bonds | C48: Debentures / bonds | D48: MF_INV_DB | E48: 0 | F48: 0
A49: 5 | B49: Investments - Debentures / Bonds | C49: Total — Investments - Debentures / Bonds | D49: __TOTAL__ | E49: =SUM(E48:E48) | F49: =SUM(F48:F48)
A50: 6 | B50: Investments - Government Securities | C50: Government securities | D50: MF_INV_GS | E50: 0 | F50: 0
A51: 6 | B51: Investments - Government Securities | C51: Total — Investments - Government Securities | D51: __TOTAL__ | E51: =SUM(E50:E50) | F51: =SUM(F50:F50)
A52: 7 | B52: Investments - Money Market Instruments | C52: Money market instruments | D52: MF_INV_MM | E52: 0 | F52: 0
A53: 7 | B53: Investments - Money Market Instruments | C53: Total — Investments - Money Market Instruments | D53: __TOTAL__ | E53: =SUM(E52:E52) | F53: =SUM(F52:F52)
A54: 8 | B54: Other Investments | C54: Other investments | D54: MF_INV_OTHER | E54: 0 | F54: 0
A55: 8 | B55: Other Investments | C55: Total — Other Investments | D55: __TOTAL__ | E55: =SUM(E54:E54) | F55: =SUM(F54:F54)
A56: 9 | B56: Current Assets | C56: Cash / bank | D56: MF_CA_CASH | E56: 0 | F56: 0
A57: 9 | B57: Current Assets | C57: Receivables | D57: MF_CA_REC | E57: 0 | F57: 0
A58: 9 | B58: Current Assets | C58: Other current assets | D58: MF_CA_OTHER | E58: 0 | F58: 0
A59: 9 | B59: Current Assets | C59: Total — Current Assets | D59: __TOTAL__ | E59: =SUM(E56:E58) | F59: =SUM(F56:F58)
A60: 10 | B60: Current Liabilities and Provisions | C60: Current liabilities | D60: MF_CL | E60: 0 | F60: 0
A61: 10 | B61: Current Liabilities and Provisions | C61: Provisions | D61: MF_PROV | E61: 0 | F61: 0
A62: 10 | B62: Current Liabilities and Provisions | C62: Total — Current Liabilities and Provisions | D62: __TOTAL__ | E62: =SUM(E60:E61) | F62: =SUM(F60:F61)
A63: 11 | B63: Investment Income | C63: Interest / dividend income | D63: MF_INC_INV | E63: 0 | F63: 0
A64: 11 | B64: Investment Income | C64: Total — Investment Income | D64: __TOTAL__ | E64: =SUM(E63:E63) | F64: =SUM(F63:F63)
A65: 12 | B65: Profit / Loss on Sale of Investments | C65: Realised gain / loss | D65: MF_GAIN_REAL | E65: 0 | F65: 0
A66: 12 | B66: Profit / Loss on Sale of Investments | C66: Total — Profit / Loss on Sale of Investments | D66: __TOTAL__ | E66: =SUM(E65:E65) | F66: =SUM(F65:F65)
A67: 13 | B67: Unrealised Appreciation / Depreciation | C67: Unrealised gain / loss | D67: MF_GAIN_UNR | E67: 0 | F67: 0
A68: 13 | B68: Unrealised Appreciation / Depreciation | C68: Total — Unrealised Appreciation / Depreciation | D68: __TOTAL__ | E68: =SUM(E67:E67) | F68: =SUM(F67:F67)
A69: 14 | B69: Management Fees | C69: Management fees | D69: MF_FEE_MGMT | E69: 0 | F69: 0
A70: 14 | B70: Management Fees | C70: Total — Management Fees | D70: __TOTAL__ | E70: =SUM(E69:E69) | F70: =SUM(F69:F69)
A71: 15 | B71: Trustee / Custodian / Other Expenses | C71: Trustee / custodian / other expenses | D71: MF_EXP_OTHER | E71: 0 | F71: 0
A72: 15 | B72: Trustee / Custodian / Other Expenses | C72: Total — Trustee / Custodian / Other Expenses | D72: __TOTAL__ | E72: =SUM(E71:E71) | F72: =SUM(F71:F71)
A73: 16 | B73: NAV / Unit Movement | C73: NAV per unit / unit movement | D73: MF_NAV | E73: 0 | F73: 0
A74: 16 | B74: NAV / Unit Movement | C74: Total — NAV / Unit Movement | D74: __TOTAL__ | E74: =SUM(E73:E73) | F74: =SUM(F73:F73)
A77: Unit Capital & NAV Movement
A78: Line Item | B78: AAH Mapping Key | C78: Current Period | D78: Previous Period | E78: Calculation / Rule | F78: Status | G78: Remarks
A79: Opening units | B79: NAV_OPEN_UNITS | C79: 0 | D79: 0 | E79: To be populated/calculated by AAH mapping engine
A80: Units issued | B80: NAV_ISS_UNITS | C80: 0 | D80: 0 | E80: To be populated/calculated by AAH mapping engine
A81: Units redeemed | B81: NAV_RED_UNITS | C81: 0 | D81: 0 | E81: To be populated/calculated by AAH mapping engine
A82: Closing units | B82: NAV_CLOSE_UNITS | C82: 0 | D82: 0 | E82: To be populated/calculated by AAH mapping engine
A83: Net assets | B83: NAV_NETASSETS | C83: 0 | D83: 0 | E83: To be populated/calculated by AAH mapping engine
A84: NAV per unit | B84: NAV_PERUNIT | C84: 0 | D84: 0 | E84: To be populated/calculated by AAH mapping engine
A87: Validation
A88: Check | B88: Current Period | C88: Previous Period | D88: Result
A89: Balance Sheet difference | B89: =C21-C12 | C89: =D21-D12 | D89: =IF(AND(ABS(B89)<1,ABS(C89)<1),"PASS","CHECK")
A90: Notes / disclosures | B90: Review | C90: Review | D90: Review
A91: Profile readiness | D91: =IF(D89="PASS","READY FOR REVIEW","NOT READY")
A95: Signatures / Certification
A96: Entity Signatory | B96: ='AAH Basic Info'!B13 | C96: Designation | D96: ='AAH Basic Info'!B14 | E96: DIN | F96: ='AAH Basic Info'!B15
A97: Signing Date | B97: ='AAH Basic Info'!B16 | C97: Place | D97: ='AAH Basic Info'!B17
A98: Audit Firm | B98: ='AAH Basic Info'!B18 | C98: FRN | D98: ='AAH Basic Info'!B19
A99: Signing CA | B99: ='AAH Basic Info'!B20 | C99: Designation | D99: ='AAH Basic Info'!B21 | E99: Membership No. | F99: ='AAH Basic Info'!B22
A100: Audit Place | B100: ='AAH Basic Info'!B23 | C100: Signing Date | D100: ='AAH Basic Info'!B30

Sheet CIS
A1: Collective Investment Scheme
A2: Authority: SEBI | Official source: https://www.sebi.gov.in/acts/cisreg.html
A3: =IF('AAH Basic Info'!B5="","","Address: "&'AAH Basic Info'!B5) | B3: =IF('AAH Basic Info'!B6="","","PAN: "&'AAH Basic Info'!B6) | C3: =IF('AAH Basic Info'!B7="","","GSTIN: "&'AAH Basic Info'!B7) | D3: =IF('AAH Basic Info'!B27="","",'AAH Basic Info'!B27)
A4: Entity Name | B4: Current Period | C4: Previous Period | D4: Presentation Unit | E4: Standalone / Consolidated
A5: =IF('AAH Basic Info'!B3="","",'AAH Basic Info'!B3) | B5: =IF('AAH Basic Info'!B9="","",'AAH Basic Info'!B9) | C5: =IF('AAH Basic Info'!B10="","",'AAH Basic Info'!B10) | D5: =IF('AAH Basic Info'!B24="","",'AAH Basic Info'!B24) | E5: =IF('AAH Basic Info'!B25="","",'AAH Basic Info'!B25)
A6: Scheme-wise Balance Sheet
A7: Particulars | B7: Note No. | C7: Current Reporting Period | D7: Previous Reporting Period
A8: ASSETS
A9: Fixed Assets | B9: 1 | C9: =E36 | D9: =F36
A10: Investments | B10: 2 | C10: =E38 | D10: =F38
A11: Project / Development Expenditure | B11: 3 | C11: =E40 | D11: =F40
A12: Current Assets | B12: 4 | C12: =E42 | D12: =F42
A13: Deferred Revenue Expenditure | B13: 5 | C13: =E44 | D13: =F44
A14: TOTAL ASSETS | C14: =SUM(C9,C10,C11,C12,C13) | D14: =SUM(D9,D10,D11,D12,D13)
A15: LIABILITIES
A16: Unit / Scheme Capital | B16: 6 | C16: =E46 | D16: =F46
A17: Reserves / Surplus | B17: 7 | C17: =E48 | D17: =F48
A18: Current Liabilities and Provisions | B18: 8 | C18: =E51 | D18: =F51
A19: TOTAL LIABILITIES | C19: =SUM(C16,C17,C18) | D19: =SUM(D16,D17,D18)
A22: Scheme-wise Revenue Account
A23: Particulars | B23: Note No. | C23: Current Reporting Period | D23: Previous Reporting Period
A24: REVENUE ACCOUNT
A25: Scheme Income | B25: 9 | C25: =E53 | D25: =F53
A26: Project / Scheme Operating Expenses | B26: 10 | C26: =E55 | D26: =F55
A27: Management / Trustee Expenses | B27: 11 | C27: =E57 | D27: =F57
A28: Depreciation | B28: 12 | C28: =E59 | D28: =F59
A29: Other Expenses | B29: 13 | C29: =E61 | D29: =F61
A30: Surplus / (Deficit) | C30: =0 | D30: =0
A33: Notes / Schedules — linked source for face statements
A34: Note | B34: Note Title | C34: Statutory Line Item | D34: AAH Mapping Key | E34: Current Period | F34: Previous Period | G34: Disclosure / Remarks
A35: 1 | B35: Fixed Assets | C35: Fixed assets | D35: CIS_FA | E35: 0 | F35: 0
A36: 1 | B36: Fixed Assets | C36: Total — Fixed Assets | D36: __TOTAL__ | E36: =SUM(E35:E35) | F36: =SUM(F35:F35)
A37: 2 | B37: Investments | C37: Investments | D37: CIS_INV | E37: 0 | F37: 0
A38: 2 | B38: Investments | C38: Total — Investments | D38: __TOTAL__ | E38: =SUM(E37:E37) | F38: =SUM(F37:F37)
A39: 3 | B39: Project / Development Expenditure | C39: Project / development expenditure | D39: CIS_DEV | E39: 0 | F39: 0
A40: 3 | B40: Project / Development Expenditure | C40: Total — Project / Development Expenditure | D40: __TOTAL__ | E40: =SUM(E39:E39) | F40: =SUM(F39:F39)
A41: 4 | B41: Current Assets | C41: Current assets | D41: CIS_CA | E41: 0 | F41: 0
A42: 4 | B42: Current Assets | C42: Total — Current Assets | D42: __TOTAL__ | E42: =SUM(E41:E41) | F42: =SUM(F41:F41)
A43: 5 | B43: Deferred Revenue Expenditure | C43: Deferred revenue expenditure | D43: CIS_DRE | E43: 0 | F43: 0
A44: 5 | B44: Deferred Revenue Expenditure | C44: Total — Deferred Revenue Expenditure | D44: __TOTAL__ | E44: =SUM(E43:E43) | F44: =SUM(F43:F43)
A45: 6 | B45: Unit / Scheme Capital | C45: Unit / scheme capital | D45: CIS_CAP | E45: 0 | F45: 0
A46: 6 | B46: Unit / Scheme Capital | C46: Total — Unit / Scheme Capital | D46: __TOTAL__ | E46: =SUM(E45:E45) | F46: =SUM(F45:F45)
A47: 7 | B47: Reserves / Surplus | C47: Reserves / surplus | D47: CIS_RES | E47: 0 | F47: 0
A48: 7 | B48: Reserves / Surplus | C48: Total — Reserves / Surplus | D48: __TOTAL__ | E48: =SUM(E47:E47) | F48: =SUM(F47:F47)
A49: 8 | B49: Current Liabilities and Provisions | C49: Current liabilities | D49: CIS_CL | E49: 0 | F49: 0
A50: 8 | B50: Current Liabilities and Provisions | C50: Provisions | D50: CIS_PROV | E50: 0 | F50: 0
A51: 8 | B51: Current Liabilities and Provisions | C51: Total — Current Liabilities and Provisions | D51: __TOTAL__ | E51: =SUM(E49:E50) | F51: =SUM(F49:F50)
A52: 9 | B52: Scheme Income | C52: Scheme income | D52: CIS_INC | E52: 0 | F52: 0
A53: 9 | B53: Scheme Income | C53: Total — Scheme Income | D53: __TOTAL__ | E53: =SUM(E52:E52) | F53: =SUM(F52:F52)
A54: 10 | B54: Project / Scheme Operating Expenses | C54: Operating expenses | D54: CIS_OPEX | E54: 0 | F54: 0
A55: 10 | B55: Project / Scheme Operating Expenses | C55: Total — Project / Scheme Operating Expenses | D55: __TOTAL__ | E55: =SUM(E54:E54) | F55: =SUM(F54:F54)
A56: 11 | B56: Management / Trustee Expenses | C56: Management / trustee expenses | D56: CIS_MGMT | E56: 0 | F56: 0
A57: 11 | B57: Management / Trustee Expenses | C57: Total — Management / Trustee Expenses | D57: __TOTAL__ | E57: =SUM(E56:E56) | F57: =SUM(F56:F56)
A58: 12 | B58: Depreciation | C58: Depreciation | D58: CIS_DEP | E58: 0 | F58: 0
A59: 12 | B59: Depreciation | C59: Total — Depreciation | D59: __TOTAL__ | E59: =SUM(E58:E58) | F59: =SUM(F58:F58)
A60: 13 | B60: Other Expenses | C60: Other expenses | D60: CIS_OTHER | E60: 0 | F60: 0
A61: 13 | B61: Other Expenses | C61: Total — Other Expenses | D61: __TOTAL__ | E61: =SUM(E60:E60) | F61: =SUM(F60:F60)
A64: Validation
A65: Check | B65: Current Period | C65: Previous Period | D65: Result
A66: Balance Sheet difference | B66: =C14-C19 | C66: =D14-D19 | D66: =IF(AND(ABS(B66)<1,ABS(C66)<1),"PASS","CHECK")
A67: Notes / disclosures | B67: Review | C67: Review | D67: Review
A68: Profile readiness | D68: =IF(D66="PASS","READY FOR REVIEW","NOT READY")
A72: Signatures / Certification
A73: Entity Signatory | B73: ='AAH Basic Info'!B13 | C73: Designation | D73: ='AAH Basic Info'!B14 | E73: DIN | F73: ='AAH Basic Info'!B15
A74: Signing Date | B74: ='AAH Basic Info'!B16 | C74: Place | D74: ='AAH Basic Info'!B17
A75: Audit Firm | B75: ='AAH Basic Info'!B18 | C75: FRN | D75: ='AAH Basic Info'!B19
A76: Signing CA | B76: ='AAH Basic Info'!B20 | C76: Designation | D76: ='AAH Basic Info'!B21 | E76: Membership No. | F76: ='AAH Basic Info'!B22
A77: Audit Place | B77: ='AAH Basic Info'!B23 | C77: Signing Date | D77: ='AAH Basic Info'!B30

Sheet REIT
A1: Real Estate Investment Trust
A2: Authority: SEBI | Official source: https://www.sebi.gov.in/web/?file=https%3A%2F%2Fwww.sebi.gov.in%2Fsebi_data%2Fattachdocs%2Fmay-2025%2F1746617164275.pdf
A3: =IF('AAH Basic Info'!B5="","","Address: "&'AAH Basic Info'!B5) | B3: =IF('AAH Basic Info'!B6="","","PAN: "&'AAH Basic Info'!B6) | C3: =IF('AAH Basic Info'!B7="","","GSTIN: "&'AAH Basic Info'!B7) | D3: =IF('AAH Basic Info'!B27="","",'AAH Basic Info'!B27)
A4: Entity Name | B4: Current Period | C4: Previous Period | D4: Presentation Unit | E4: Standalone / Consolidated
A5: =IF('AAH Basic Info'!B3="","",'AAH Basic Info'!B3) | B5: =IF('AAH Basic Info'!B9="","",'AAH Basic Info'!B9) | C5: =IF('AAH Basic Info'!B10="","",'AAH Basic Info'!B10) | D5: =IF('AAH Basic Info'!B24="","",'AAH Basic Info'!B24) | E5: =IF('AAH Basic Info'!B25="","",'AAH Basic Info'!B25)
A6: Statement of Assets and Liabilities / Balance Sheet
A7: Particulars | B7: Note No. | C7: Current Reporting Period | D7: Previous Reporting Period
A8: ASSETS
A9: Investment Property / Infrastructure Assets | B9: 3 | C9: =E48 | D9: =F48
A10: Property, Plant and Equipment | B10: 4 | C10: =E50 | D10: =F50
A11: Investments in SPVs / HoldCos | B11: 5 | C11: =E52 | D11: =F52
A12: Other Financial Assets | B12: 6 | C12: =E54 | D12: =F54
A13: Cash and Bank Balances | B13: 7 | C13: =E56 | D13: =F56
A14: Other Assets | B14: 8 | C14: =E58 | D14: =F58
A15: TOTAL ASSETS | C15: =SUM(C9,C10,C11,C12,C13,C14) | D15: =SUM(D9,D10,D11,D12,D13,D14)
A16: EQUITY AND LIABILITIES
A17: Unit Capital | B17: 1 | C17: =E44 | D17: =F44
A18: Other Equity / Reserves | B18: 2 | C18: =E46 | D18: =F46
A19: Borrowings / Debt Securities | B19: 9 | C19: =E60 | D19: =F60
A20: Trade and Other Payables | B20: 10 | C20: =E62 | D20: =F62
A21: Other Financial Liabilities | B21: 11 | C21: =E64 | D21: =F64
A22: Other Liabilities / Provisions | B22: 12 | C22: =E66 | D22: =F66
A23: TOTAL EQUITY AND LIABILITIES | C23: =SUM(C17,C18,C19,C20,C21,C22) | D23: =SUM(D17,D18,D19,D20,D21,D22)
A26: Statement of Profit and Loss
A27: Particulars | B27: Note No. | C27: Current Reporting Period | D27: Previous Reporting Period
A28: Revenue from Operations | B28: 13 | C28: =E68 | D28: =F68
A29: Other Income | B29: 14 | C29: =E70 | D29: =F70
A30: TOTAL INCOME | C30: =SUM(C28,C29) | D30: =SUM(D28,D29)
A31: EXPENSES
A32: Finance Costs | B32: 15 | C32: =E72 | D32: =F72
A33: Operating / Property Expenses | B33: 16 | C33: =E74 | D33: =F74
A34: Manager / Employee Fees | B34: 17 | C34: =E76 | D34: =F76
A35: Depreciation / Amortisation | B35: 18 | C35: =E78 | D35: =F78
A36: Other Expenses | B36: 19 | C36: =E80 | D36: =F80
A37: TOTAL EXPENSES | C37: =SUM(C32,C33,C34,C35,C36) | D37: =SUM(D32,D33,D34,D35,D36)
A38: Profit / (Loss) for the Period | C38: =C30-C37 | D38: =D30-D37
A41: Notes / Schedules — linked source for face statements
A42: Note | B42: Note Title | C42: Statutory Line Item | D42: AAH Mapping Key | E42: Current Period | F42: Previous Period | G42: Disclosure / Remarks
A43: 1 | B43: Unit Capital | C43: Unit capital | D43: UNIT_CAP | E43: 0 | F43: 0
A44: 1 | B44: Unit Capital | C44: Total — Unit Capital | D44: __TOTAL__ | E44: =SUM(E43:E43) | F44: =SUM(F43:F43)
A45: 2 | B45: Other Equity / Reserves | C45: Other equity / reserves | D45: OTHER_EQ | E45: 0 | F45: 0
A46: 2 | B46: Other Equity / Reserves | C46: Total — Other Equity / Reserves | D46: __TOTAL__ | E46: =SUM(E45:E45) | F46: =SUM(F45:F45)
A47: 3 | B47: Investment Property / Infrastructure Assets | C47: Investment property / infrastructure assets | D47: INV_ASSET | E47: 0 | F47: 0
A48: 3 | B48: Investment Property / Infrastructure Assets | C48: Total — Investment Property / Infrastructure Assets | D48: __TOTAL__ | E48: =SUM(E47:E47) | F48: =SUM(F47:F47)
A49: 4 | B49: Property, Plant and Equipment | C49: PPE | D49: PPE | E49: 0 | F49: 0
A50: 4 | B50: Property, Plant and Equipment | C50: Total — Property, Plant and Equipment | D50: __TOTAL__ | E50: =SUM(E49:E49) | F50: =SUM(F49:F49)
A51: 5 | B51: Investments in SPVs / HoldCos | C51: Investments in SPVs / HoldCos | D51: INV_SPV | E51: 0 | F51: 0
A52: 5 | B52: Investments in SPVs / HoldCos | C52: Total — Investments in SPVs / HoldCos | D52: __TOTAL__ | E52: =SUM(E51:E51) | F52: =SUM(F51:F51)
A53: 6 | B53: Other Financial Assets | C53: Other financial assets | D53: OFA | E53: 0 | F53: 0
A54: 6 | B54: Other Financial Assets | C54: Total — Other Financial Assets | D54: __TOTAL__ | E54: =SUM(E53:E53) | F54: =SUM(F53:F53)
A55: 7 | B55: Cash and Bank Balances | C55: Cash and bank balances | D55: CASH | E55: 0 | F55: 0
A56: 7 | B56: Cash and Bank Balances | C56: Total — Cash and Bank Balances | D56: __TOTAL__ | E56: =SUM(E55:E55) | F56: =SUM(F55:F55)
A57: 8 | B57: Other Assets | C57: Other assets | D57: OA | E57: 0 | F57: 0
A58: 8 | B58: Other Assets | C58: Total — Other Assets | D58: __TOTAL__ | E58: =SUM(E57:E57) | F58: =SUM(F57:F57)
A59: 9 | B59: Borrowings / Debt Securities | C59: Borrowings / debt securities | D59: BORR | E59: 0 | F59: 0
A60: 9 | B60: Borrowings / Debt Securities | C60: Total — Borrowings / Debt Securities | D60: __TOTAL__ | E60: =SUM(E59:E59) | F60: =SUM(F59:F59)
A61: 10 | B61: Trade and Other Payables | C61: Trade and other payables | D61: PAY | E61: 0 | F61: 0
A62: 10 | B62: Trade and Other Payables | C62: Total — Trade and Other Payables | D62: __TOTAL__ | E62: =SUM(E61:E61) | F62: =SUM(F61:F61)
A63: 11 | B63: Other Financial Liabilities | C63: Other financial liabilities | D63: OFL | E63: 0 | F63: 0
A64: 11 | B64: Other Financial Liabilities | C64: Total — Other Financial Liabilities | D64: __TOTAL__ | E64: =SUM(E63:E63) | F64: =SUM(F63:F63)
A65: 12 | B65: Other Liabilities / Provisions | C65: Other liabilities / provisions | D65: OLP | E65: 0 | F65: 0
A66: 12 | B66: Other Liabilities / Provisions | C66: Total — Other Liabilities / Provisions | D66: __TOTAL__ | E66: =SUM(E65:E65) | F66: =SUM(F65:F65)
A67: 13 | B67: Revenue from Operations | C67: Revenue from operations | D67: REV | E67: 0 | F67: 0
A68: 13 | B68: Revenue from Operations | C68: Total — Revenue from Operations | D68: __TOTAL__ | E68: =SUM(E67:E67) | F68: =SUM(F67:F67)
A69: 14 | B69: Other Income | C69: Other income | D69: OI | E69: 0 | F69: 0
A70: 14 | B70: Other Income | C70: Total — Other Income | D70: __TOTAL__ | E70: =SUM(E69:E69) | F70: =SUM(F69:F69)
A71: 15 | B71: Finance Costs | C71: Finance costs | D71: FIN | E71: 0 | F71: 0
A72: 15 | B72: Finance Costs | C72: Total — Finance Costs | D72: __TOTAL__ | E72: =SUM(E71:E71) | F72: =SUM(F71:F71)
A73: 16 | B73: Operating / Property Expenses | C73: Operating / property expenses | D73: OPEX | E73: 0 | F73: 0
A74: 16 | B74: Operating / Property Expenses | C74: Total — Operating / Property Expenses | D74: __TOTAL__ | E74: =SUM(E73:E73) | F74: =SUM(F73:F73)
A75: 17 | B75: Manager / Employee Fees | C75: Manager / employee fees | D75: MGMT | E75: 0 | F75: 0
A76: 17 | B76: Manager / Employee Fees | C76: Total — Manager / Employee Fees | D76: __TOTAL__ | E76: =SUM(E75:E75) | F76: =SUM(F75:F75)
A77: 18 | B77: Depreciation / Amortisation | C77: Depreciation / amortisation | D77: DEPAM | E77: 0 | F77: 0
A78: 18 | B78: Depreciation / Amortisation | C78: Total — Depreciation / Amortisation | D78: __TOTAL__ | E78: =SUM(E77:E77) | F78: =SUM(F77:F77)
A79: 19 | B79: Other Expenses | C79: Other expenses | D79: OE | E79: 0 | F79: 0
A80: 19 | B80: Other Expenses | C80: Total — Other Expenses | D80: __TOTAL__ | E80: =SUM(E79:E79) | F80: =SUM(F79:F79)
A81: 20 | B81: Net Assets at Fair Value | C81: Net assets at fair value | D81: NAV_FV | E81: 0 | F81: 0
A82: 20 | B82: Net Assets at Fair Value | C82: Total — Net Assets at Fair Value | D82: __TOTAL__ | E82: =SUM(E81:E81) | F82: =SUM(F81:F81)
A83: 21 | B83: Total Returns at Fair Value | C83: Total returns at fair value | D83: TR_FV | E83: 0 | F83: 0
A84: 21 | B84: Total Returns at Fair Value | C84: Total — Total Returns at Fair Value | D84: __TOTAL__ | E84: =SUM(E83:E83) | F84: =SUM(F83:F83)
A85: 22 | B85: Distributions / NDCF | C85: Distributions / NDCF | D85: NDCF | E85: 0 | F85: 0
A86: 22 | B86: Distributions / NDCF | C86: Total — Distributions / NDCF | D86: __TOTAL__ | E86: =SUM(E85:E85) | F86: =SUM(F85:F85)
A89: Cash Flow Statement
A90: Line Item | B90: AAH Mapping Key | C90: Current Period | D90: Previous Period | E90: Calculation / Rule | F90: Status | G90: Remarks
A91: Profit before tax / operating surplus | B91: CFS_PBT | C91: 0 | D91: 0 | E91: To be populated/calculated by AAH mapping engine
A92: Non-cash adjustments | B92: CFS_ADJ | C92: 0 | D92: 0 | E92: To be populated/calculated by AAH mapping engine
A93: Working capital changes | B93: CFS_WC | C93: 0 | D93: 0 | E93: To be populated/calculated by AAH mapping engine
A94: Taxes paid | B94: CFS_TAX | C94: 0 | D94: 0 | E94: To be populated/calculated by AAH mapping engine
A95: Net cash from operating activities | B95: CFS_CFO | C95: 0 | D95: 0 | E95: To be populated/calculated by AAH mapping engine
A96: Net cash from investing activities | B96: CFS_CFI | C96: 0 | D96: 0 | E96: To be populated/calculated by AAH mapping engine
A97: Net cash from financing activities | B97: CFS_CFF | C97: 0 | D97: 0 | E97: To be populated/calculated by AAH mapping engine
A98: Net increase / (decrease) in cash | B98: CFS_NET | C98: 0 | D98: 0 | E98: To be populated/calculated by AAH mapping engine
A99: Opening cash and cash equivalents | B99: CFS_OPEN | C99: 0 | D99: 0 | E99: To be populated/calculated by AAH mapping engine
A100: Closing cash and cash equivalents | B100: CFS_CLOSE | C100: 0 | D100: 0 | E100: To be populated/calculated by AAH mapping engine
A103: Statement of Changes in Equity / Unitholders' Equity
A104: Line Item | B104: AAH Mapping Key | C104: Current Period | D104: Previous Period | E104: Calculation / Rule | F104: Status | G104: Remarks
A105: Opening equity / unit capital | B105: SOE_OPEN | C105: 0 | D105: 0 | E105: To be populated/calculated by AAH mapping engine
A106: Changes in capital / units | B106: SOE_CAPCHG | C106: 0 | D106: 0 | E106: To be populated/calculated by AAH mapping engine
A107: Profit / loss for period | B107: SOE_PL | C107: 0 | D107: 0 | E107: To be populated/calculated by AAH mapping engine
A108: Other comprehensive income / fair value movement | B108: SOE_OCI | C108: 0 | D108: 0 | E108: To be populated/calculated by AAH mapping engine
...

Sheet INVIT
A1: Infrastructure Investment Trust
A2: Authority: SEBI | Official source: https://www.sebi.gov.in/sebi_data/attachdocs/jul-2025/1752576381910.pdf
A3: =IF('AAH Basic Info'!B5="","","Address: "&'AAH Basic Info'!B5) | B3: =IF('AAH Basic Info'!B6="","","PAN: "&'AAH Basic Info'!B6) | C3: =IF('AAH Basic Info'!B7="","","GSTIN: "&'AAH Basic Info'!B7) | D3: =IF('AAH Basic Info'!B27="","",'AAH Basic Info'!B27)
A4: Entity Name | B4: Current Period | C4: Previous Period | D4: Presentation Unit | E4: Standalone / Consolidated
A5: =IF('AAH Basic Info'!B3="","",'AAH Basic Info'!B3) | B5: =IF('AAH Basic Info'!B9="","",'AAH Basic Info'!B9) | C5: =IF('AAH Basic Info'!B10="","",'AAH Basic Info'!B10) | D5: =IF('AAH Basic Info'!B24="","",'AAH Basic Info'!B24) | E5: =IF('AAH Basic Info'!B25="","",'AAH Basic Info'!B25)
A6: Statement of Assets and Liabilities / Balance Sheet
A7: Particulars | B7: Note No. | C7: Current Reporting Period | D7: Previous Reporting Period
A8: ASSETS
A9: Investment Property / Infrastructure Assets | B9: 3 | C9: =E48 | D9: =F48
A10: Property, Plant and Equipment | B10: 4 | C10: =E50 | D10: =F50
A11: Investments in SPVs / HoldCos | B11: 5 | C11: =E52 | D11: =F52
A12: Other Financial Assets | B12: 6 | C12: =E54 | D12: =F54
A13: Cash and Bank Balances | B13: 7 | C13: =E56 | D13: =F56
A14: Other Assets | B14: 8 | C14: =E58 | D14: =F58
A15: TOTAL ASSETS | C15: =SUM(C9,C10,C11,C12,C13,C14) | D15: =SUM(D9,D10,D11,D12,D13,D14)
A16: EQUITY AND LIABILITIES
A17: Unit Capital | B17: 1 | C17: =E44 | D17: =F44
A18: Other Equity / Reserves | B18: 2 | C18: =E46 | D18: =F46
A19: Borrowings / Debt Securities | B19: 9 | C19: =E60 | D19: =F60
A20: Trade and Other Payables | B20: 10 | C20: =E62 | D20: =F62
A21: Other Financial Liabilities | B21: 11 | C21: =E64 | D21: =F64
A22: Other Liabilities / Provisions | B22: 12 | C22: =E66 | D22: =F66
A23: TOTAL EQUITY AND LIABILITIES | C23: =SUM(C17,C18,C19,C20,C21,C22) | D23: =SUM(D17,D18,D19,D20,D21,D22)
A26: Statement of Profit and Loss
A27: Particulars | B27: Note No. | C27: Current Reporting Period | D27: Previous Reporting Period
A28: Revenue from Operations | B28: 13 | C28: =E68 | D28: =F68
A29: Other Income | B29: 14 | C29: =E70 | D29: =F70
A30: TOTAL INCOME | C30: =SUM(C28,C29) | D30: =SUM(D28,D29)
A31: EXPENSES
A32: Finance Costs | B32: 15 | C32: =E72 | D32: =F72
A33: Operating / Property Expenses | B33: 16 | C33: =E74 | D33: =F74
A34: Manager / Employee Fees | B34: 17 | C34: =E76 | D34: =F76
A35: Depreciation / Amortisation | B35: 18 | C35: =E78 | D35: =F78
A36: Other Expenses | B36: 19 | C36: =E80 | D36: =F80
A37: TOTAL EXPENSES | C37: =SUM(C32,C33,C34,C35,C36) | D37: =SUM(D32,D33,D34,D35,D36)
A38: Profit / (Loss) for the Period | C38: =C30-C37 | D38: =D30-D37
A41: Notes / Schedules — linked source for face statements
A42: Note | B42: Note Title | C42: Statutory Line Item | D42: AAH Mapping Key | E42: Current Period | F42: Previous Period | G42: Disclosure / Remarks
A43: 1 | B43: Unit Capital | C43: Unit capital | D43: UNIT_CAP | E43: 0 | F43: 0
A44: 1 | B44: Unit Capital | C44: Total — Unit Capital | D44: __TOTAL__ | E44: =SUM(E43:E43) | F44: =SUM(F43:F43)
A45: 2 | B45: Other Equity / Reserves | C45: Other equity / reserves | D45: OTHER_EQ | E45: 0 | F45: 0
A46: 2 | B46: Other Equity / Reserves | C46: Total — Other Equity / Reserves | D46: __TOTAL__ | E46: =SUM(E45:E45) | F46: =SUM(F45:F45)
A47: 3 | B47: Investment Property / Infrastructure Assets | C47: Investment property / infrastructure assets | D47: INV_ASSET | E47: 0 | F47: 0
A48: 3 | B48: Investment Property / Infrastructure Assets | C48: Total — Investment Property / Infrastructure Assets | D48: __TOTAL__ | E48: =SUM(E47:E47) | F48: =SUM(F47:F47)
A49: 4 | B49: Property, Plant and Equipment | C49: PPE | D49: PPE | E49: 0 | F49: 0
A50: 4 | B50: Property, Plant and Equipment | C50: Total — Property, Plant and Equipment | D50: __TOTAL__ | E50: =SUM(E49:E49) | F50: =SUM(F49:F49)
A51: 5 | B51: Investments in SPVs / HoldCos | C51: Investments in SPVs / HoldCos | D51: INV_SPV | E51: 0 | F51: 0
A52: 5 | B52: Investments in SPVs / HoldCos | C52: Total — Investments in SPVs / HoldCos | D52: __TOTAL__ | E52: =SUM(E51:E51) | F52: =SUM(F51:F51)
A53: 6 | B53: Other Financial Assets | C53: Other financial assets | D53: OFA | E53: 0 | F53: 0
A54: 6 | B54: Other Financial Assets | C54: Total — Other Financial Assets | D54: __TOTAL__ | E54: =SUM(E53:E53) | F54: =SUM(F53:F53)
A55: 7 | B55: Cash and Bank Balances | C55: Cash and bank balances | D55: CASH | E55: 0 | F55: 0
A56: 7 | B56: Cash and Bank Balances | C56: Total — Cash and Bank Balances | D56: __TOTAL__ | E56: =SUM(E55:E55) | F56: =SUM(F55:F55)
A57: 8 | B57: Other Assets | C57: Other assets | D57: OA | E57: 0 | F57: 0
A58: 8 | B58: Other Assets | C58: Total — Other Assets | D58: __TOTAL__ | E58: =SUM(E57:E57) | F58: =SUM(F57:F57)
A59: 9 | B59: Borrowings / Debt Securities | C59: Borrowings / debt securities | D59: BORR | E59: 0 | F59: 0
A60: 9 | B60: Borrowings / Debt Securities | C60: Total — Borrowings / Debt Securities | D60: __TOTAL__ | E60: =SUM(E59:E59) | F60: =SUM(F59:F59)
A61: 10 | B61: Trade and Other Payables | C61: Trade and other payables | D61: PAY | E61: 0 | F61: 0
A62: 10 | B62: Trade and Other Payables | C62: Total — Trade and Other Payables | D62: __TOTAL__ | E62: =SUM(E61:E61) | F62: =SUM(F61:F61)
A63: 11 | B63: Other Financial Liabilities | C63: Other financial liabilities | D63: OFL | E63: 0 | F63: 0
A64: 11 | B64: Other Financial Liabilities | C64: Total — Other Financial Liabilities | D64: __TOTAL__ | E64: =SUM(E63:E63) | F64: =SUM(F63:F63)
A65: 12 | B65: Other Liabilities / Provisions | C65: Other liabilities / provisions | D65: OLP | E65: 0 | F65: 0
A66: 12 | B66: Other Liabilities / Provisions | C66: Total — Other Liabilities / Provisions | D66: __TOTAL__ | E66: =SUM(E65:E65) | F66: =SUM(F65:F65)
A67: 13 | B67: Revenue from Operations | C67: Revenue from operations | D67: REV | E67: 0 | F67: 0
A68: 13 | B68: Revenue from Operations | C68: Total — Revenue from Operations | D68: __TOTAL__ | E68: =SUM(E67:E67) | F68: =SUM(F67:F67)
A69: 14 | B69: Other Income | C69: Other income | D69: OI | E69: 0 | F69: 0
A70: 14 | B70: Other Income | C70: Total — Other Income | D70: __TOTAL__ | E70: =SUM(E69:E69) | F70: =SUM(F69:F69)
A71: 15 | B71: Finance Costs | C71: Finance costs | D71: FIN | E71: 0 | F71: 0
A72: 15 | B72: Finance Costs | C72: Total — Finance Costs | D72: __TOTAL__ | E72: =SUM(E71:E71) | F72: =SUM(F71:F71)
A73: 16 | B73: Operating / Property Expenses | C73: Operating / property expenses | D73: OPEX | E73: 0 | F73: 0
A74: 16 | B74: Operating / Property Expenses | C74: Total — Operating / Property Expenses | D74: __TOTAL__ | E74: =SUM(E73:E73) | F74: =SUM(F73:F73)
A75: 17 | B75: Manager / Employee Fees | C75: Manager / employee fees | D75: MGMT | E75: 0 | F75: 0
A76: 17 | B76: Manager / Employee Fees | C76: Total — Manager / Employee Fees | D76: __TOTAL__ | E76: =SUM(E75:E75) | F76: =SUM(F75:F75)
A77: 18 | B77: Depreciation / Amortisation | C77: Depreciation / amortisation | D77: DEPAM | E77: 0 | F77: 0
A78: 18 | B78: Depreciation / Amortisation | C78: Total — Depreciation / Amortisation | D78: __TOTAL__ | E78: =SUM(E77:E77) | F78: =SUM(F77:F77)
A79: 19 | B79: Other Expenses | C79: Other expenses | D79: OE | E79: 0 | F79: 0
A80: 19 | B80: Other Expenses | C80: Total — Other Expenses | D80: __TOTAL__ | E80: =SUM(E79:E79) | F80: =SUM(F79:F79)
A81: 20 | B81: Net Assets at Fair Value | C81: Net assets at fair value | D81: NAV_FV | E81: 0 | F81: 0
A82: 20 | B82: Net Assets at Fair Value | C82: Total — Net Assets at Fair Value | D82: __TOTAL__ | E82: =SUM(E81:E81) | F82: =SUM(F81:F81)
A83: 21 | B83: Total Returns at Fair Value | C83: Total returns at fair value | D83: TR_FV | E83: 0 | F83: 0
A84: 21 | B84: Total Returns at Fair Value | C84: Total — Total Returns at Fair Value | D84: __TOTAL__ | E84: =SUM(E83:E83) | F84: =SUM(F83:F83)
A85: 22 | B85: Distributions / NDCF | C85: Distributions / NDCF | D85: NDCF | E85: 0 | F85: 0
A86: 22 | B86: Distributions / NDCF | C86: Total — Distributions / NDCF | D86: __TOTAL__ | E86: =SUM(E85:E85) | F86: =SUM(F85:F85)
A89: Cash Flow Statement
A90: Line Item | B90: AAH Mapping Key | C90: Current Period | D90: Previous Period | E90: Calculation / Rule | F90: Status | G90: Remarks
A91: Profit before tax / operating surplus | B91: CFS_PBT | C91: 0 | D91: 0 | E91: To be populated/calculated by AAH mapping engine
A92: Non-cash adjustments | B92: CFS_ADJ | C92: 0 | D92: 0 | E92: To be populated/calculated by AAH mapping engine
A93: Working capital changes | B93: CFS_WC | C93: 0 | D93: 0 | E93: To be populated/calculated by AAH mapping engine
A94: Taxes paid | B94: CFS_TAX | C94: 0 | D94: 0 | E94: To be populated/calculated by AAH mapping engine
A95: Net cash from operating activities | B95: CFS_CFO | C95: 0 | D95: 0 | E95: To be populated/calculated by AAH mapping engine
A96: Net cash from investing activities | B96: CFS_CFI | C96: 0 | D96: 0 | E96: To be populated/calculated by AAH mapping engine
A97: Net cash from financing activities | B97: CFS_CFF | C97: 0 | D97: 0 | E97: To be populated/calculated by AAH mapping engine
A98: Net increase / (decrease) in cash | B98: CFS_NET | C98: 0 | D98: 0 | E98: To be populated/calculated by AAH mapping engine
A99: Opening cash and cash equivalents | B99: CFS_OPEN | C99: 0 | D99: 0 | E99: To be populated/calculated by AAH mapping engine
A100: Closing cash and cash equivalents | B100: CFS_CLOSE | C100: 0 | D100: 0 | E100: To be populated/calculated by AAH mapping engine
A103: Statement of Changes in Equity / Unitholders' Equity
A104: Line Item | B104: AAH Mapping Key | C104: Current Period | D104: Previous Period | E104: Calculation / Rule | F104: Status | G104: Remarks
A105: Opening equity / unit capital | B105: SOE_OPEN | C105: 0 | D105: 0 | E105: To be populated/calculated by AAH mapping engine
A106: Changes in capital / units | B106: SOE_CAPCHG | C106: 0 | D106: 0 | E106: To be populated/calculated by AAH mapping engine
A107: Profit / loss for period | B107: SOE_PL | C107: 0 | D107: 0 | E107: To be populated/calculated by AAH mapping engine
A108: Other comprehensive income / fair value movement | B108: SOE_OCI | C108: 0 | D108: 0 | E108: To be populated/calculated by AAH mapping engine
...

Sheet 03_QA_Status
A1: AAH Financial Statement Library — QA Status
A3: Check | B3: Scope | C3: Result | D3: Evidence | E3: Action | F3: Status
A4: Profile coverage | B4: 16 statutory/regulatory profiles | C4: 16/16 present | D4: Index + profile sheets | E4: None | F4: PASS
A5: Face statements | B5: Balance Sheet + P&L/equivalent | C5: Present | D5: Each profile top section | E5: Review with real client data | F5: PASS
A6: Linked notes | B6: Face statements linked to note totals | C6: Present | D6: Formula links within profile sheet | E6: Populate mapping keys / disclosures | F6: PASS
A7: Comparatives | B7: Current + previous period columns | C7: Present | D7: All face statements and notes | E7: None | F7: PASS
A8: Special statements | B8: CFS/SOCE/NAV/NDCF where profile requires | C8: Present as structured blocks | D8: Profile special sections | E8: AAH calculation engine to populate | F8: PASS
A9: Formula integrity | B9: Workbook formula error scan | C9: No #REF/#DIV0/#VALUE/#NAME/#N/A | D9: Fresh import verification | E9: None | F9: PASS
A10: Visual presentation | B10: Company AS / NCE / Bank / REIT sampled | C10: Clean professional hierarchy | D10: Rendered previews | E10: Final print-area setup can be applied inside AAH export | F10: PASS
A11: AAH readiness | B11: Mapping keys embedded in note lines | C11: Ready for ledger mapping design | D11: AAH Mapping Key column | E11: Next phase: persistent ledger-to-key mapping | F11: PASS

Sheet AAH Basic Info
A1: AAH Financial Statements - Basic Information
A3: Entity Name
A4: Mailing Name
A5: Address
A6: PAN
A7: GSTIN
A8: Entity Type
A9: Current Year End
A10: Previous Year End
A11: Rounding
A12: PPE / FA Block
A13: Entity Signatory
... A30: CA Signing Date
